Workbook

Sheet 肉类、海鲜（涮菜）
A1: 菜品成本卡
A2: 菜品 | B2: 名称 | C2: 分类 | D2: 进货渠道 | E2: 品牌 | F2: 采购价格(元) | G2: 基础单位数量(g) | H2: 标准出成率 | I2: 基础单价(元/g) | J2: 配方用量(g) | K2: 理论成本(元) | L2: 备注
A3: 云山雪花吊龙 | B3: 吊龙 | C3: =VLOOKUP(B3,原材料价格表!$B$2:$J$242,9,) | D3: =VLOOKUP(B3,原材料价格表!$B$2:$G$436,2,0) | E3: =VLOOKUP(B3,原材料价格表!$B$2:$G$436,4,0) | F3: =VLOOKUP(B3,原材料价格表!$B$2:$G$436,6,0) | G3: =VLOOKUP(B3,原材料价格表!$B$2:$G$436,5,0) | H3: 0.9 | I3: =F3/G3/H3 | J3: 250 | K3: =I3*J3
B4: 法香 | C4: =VLOOKUP(B4,原材料价格表!$B$2:$J$242,9,) | D4: =VLOOKUP(B4,原材料价格表!$B$2:$G$436,2,0) | E4: =VLOOKUP(B4,原材料价格表!$B$2:$G$436,4,0) | F4: =VLOOKUP(B4,原材料价格表!$B$2:$G$436,6,0) | G4: =VLOOKUP(B4,原材料价格表!$B$2:$G$436,5,0) | H4: 1 | I4: =F4/G4/H4 | J4: 120 | K4: =I4*J4
B5: 干冰 | C5: =VLOOKUP(B5,原材料价格表!$B$2:$J$242,9,) | D5: =VLOOKUP(B5,原材料价格表!$B$2:$G$436,2,0) | E5: =VLOOKUP(B5,原材料价格表!$B$2:$G$436,4,0) | F5: =VLOOKUP(B5,原材料价格表!$B$2:$G$436,6,0) | G5: =VLOOKUP(B5,原材料价格表!$B$2:$G$436,5,0) | H5: 1 | I5: =F5/G5/H5 | J5: 20 | K5: =I5*J5
B6: 售价 | D6: 88 | E6: 售卖份量/g | F6: =SUM(J3:J5) | G6: 总成本（元） | H6: =SUM(K3:K5) | I6: 毛利/元 | J6: =D6-H6 | K6: 毛利率 | L6: =J6/D6
A7: 木姜子鲜黄牛肉 | B7: 吊龙 | C7: =VLOOKUP(B7,原材料价格表!$B$2:$J$242,9,) | D7: =VLOOKUP(B7,原材料价格表!$B$2:$G$436,2,0) | E7: =VLOOKUP(B7,原材料价格表!$B$2:$G$436,3,0) | F7: =VLOOKUP(B7,原材料价格表!$B$2:$G$436,6,0) | G7: =VLOOKUP(B7,原材料价格表!$B$2:$G$436,5,0) | H7: 0.9 | I7: =F7/G7/H7 | J7: 120 | K7: =I7*J7
B8: 木姜子 | C8: =VLOOKUP(B8,原材料价格表!$B$2:$J$242,9,) | D8: =VLOOKUP(B8,原材料价格表!$B$2:$G$436,2,0) | E8: =VLOOKUP(B8,原材料价格表!$B$2:$G$436,3,0) | F8: =VLOOKUP(B8,原材料价格表!$B$2:$G$436,6,0) | G8: =VLOOKUP(B8,原材料价格表!$B$2:$G$436,5,0) | H8: 1 | I8: =F8/G8/H8 | J8: 60 | K8: =I8*J8
B9: 售价 | D9: 42 | E9: 售卖份量/g | F9: =SUM(J7:J8) | G9: 总成本（元） | H9: =SUM(K7:K8) | I9: 毛利/元 | J9: =D9-H9 | K9: 毛利率 | L9: =J9/D9
A10: 糊辣椒鲜黄牛匙仁 | B10: 匙仁 | C10: =VLOOKUP(B10,原材料价格表!$B$2:$J$242,9,) | D10: =VLOOKUP(B10,原材料价格表!$B$2:$G$436,2,0) | E10: =VLOOKUP(B10,原材料价格表!$B$2:$G$436,3,0) | F10: =VLOOKUP(B10,原材料价格表!$B$2:$G$436,6,0) | G10: =VLOOKUP(B10,原材料价格表!$B$2:$G$436,5,0) | H10: 0.9 | I10: =F10/G10/H10 | J10: 120 | K10: =I10*J10
B11: 糊辣椒 | C11: =VLOOKUP(B11,原材料价格表!$B$2:$J$242,9,) | D11: =VLOOKUP(B11,原材料价格表!$B$2:$G$436,2,0) | E11: =VLOOKUP(B11,原材料价格表!$B$2:$G$436,3,0) | F11: 25 | G11: =VLOOKUP(B11,原材料价格表!$B$2:$G$436,5,0) | H11: 1 | I11: =F11/G11/H11 | J11: 25 | K11: =I11*J11
B12: 干香茅草 | C12: =VLOOKUP(B12,原材料价格表!$B$2:$J$242,9,) | D12: =VLOOKUP(B12,原材料价格表!$B$2:$G$436,2,0) | E12: =VLOOKUP(B12,原材料价格表!$B$2:$G$436,3,0) | F12: =VLOOKUP(B12,原材料价格表!$B$2:$G$436,6,0) | G12: =VLOOKUP(B12,原材料价格表!$B$2:$G$436,5,0) | H12: 1 | I12: =F12/G12/H12 | J12: 25 | K12: =I12*J12
B13: 售价 | D13: 38 | E13: 售卖份量/g | F13: =SUM(J10:J12) | G13: 总成本（元） | H13: =SUM(K10:K12) | I13: 毛利/元 | J13: =D13-H13 | K13: 毛利率 | L13: =J13/D13
A14: 野蒜酥五花趾 | B14: 五花腱 | C14: =VLOOKUP(B14,原材料价格表!$B$2:$J$242,9,) | D14: =VLOOKUP(B14,原材料价格表!$B$2:$G$436,2,0) | E14: =VLOOKUP(B14,原材料价格表!$B$2:$G$436,3,0) | F14: =VLOOKUP(B14,原材料价格表!$B$2:$G$436,6,0) | G14: =VLOOKUP(B14,原材料价格表!$B$2:$G$436,5,0) | H14: 0.9 | I14: =F14/G14/H14 | J14: 120 | K14: =I14*J14
B15: 金蒜酥 | C15: =VLOOKUP(B15,原材料价格表!$B$2:$J$242,9,) | D15: =VLOOKUP(B15,原材料价格表!$B$2:$G$436,2,0) | E15: =VLOOKUP(B15,原材料价格表!$B$2:$G$436,3,0) | F15: =VLOOKUP(B15,原材料价格表!$B$2:$G$436,6,0) | G15: =VLOOKUP(B15,原材料价格表!$B$2:$G$436,5,0) | H15: 1 | I15: =F15/G15/H15 | J15: 40 | K15: =I15*J15
B16: 售价 | D16: 38 | E16: 售卖份量/g | F16: =SUM(J14:J15) | G16: 总成本（元） | H16: =SUM(K14:K15) | I16: 毛利/元 | J16: =D16-H16 | K16: 毛利率 | L16: =J16/D16
A17: 紫苏半边云 | B17: 胸口油 | C17: =VLOOKUP(B17,原材料价格表!$B$2:$J$242,9,) | D17: =VLOOKUP(B17,原材料价格表!$B$2:$G$436,2,0) | E17: =VLOOKUP(B17,原材料价格表!$B$2:$G$436,3,0) | F17: =VLOOKUP(B17,原材料价格表!$B$2:$G$436,6,0) | G17: =VLOOKUP(B17,原材料价格表!$B$2:$G$436,5,0) | H17: 0.7 | I17: =F17/G17/H17 | J17: 120 | K17: =I17*J17
B18: 紫苏叶 | C18: =VLOOKUP(B18,原材料价格表!$B$2:$J$242,9,) | D18: =VLOOKUP(B18,原材料价格表!$B$2:$G$436,2,0) | E18: =VLOOKUP(B18,原材料价格表!$B$2:$G$436,3,0) | F18: =VLOOKUP(B18,原材料价格表!$B$2:$G$436,6,0) | G18: =VLOOKUP(B18,原材料价格表!$B$2:$G$436,5,0) | H18: 1 | I18: =F18/G18/H18 | J18: 10 | K18: =I18*J18
B19: 紫苏碎 | C19: =VLOOKUP(B19,原材料价格表!$B$2:$J$242,9,) | D19: =VLOOKUP(B19,原材料价格表!$B$2:$G$436,2,0) | E19: =VLOOKUP(B19,原材料价格表!$B$2:$G$436,3,0) | F19: =VLOOKUP(B19,原材料价格表!$B$2:$G$436,6,0) | G19: =VLOOKUP(B19,原材料价格表!$B$2:$G$436,5,0) | H19: 1 | I19: =F19/G19/H19 | J19: 5 | K19: =I19*J19
B20: 售价 | D20: 38 | E20: 售卖份量/g | F20: =SUM(J17:J19) | G20: 总成本（元） | H20: =SUM(K17:K19) | I20: 毛利/元 | J20: =D20-H20 | K20: 毛利率 | L20: =J20/D20
A21: 大地飞雪(M9纯血和牛) | B21: M9和牛 | C21: =VLOOKUP(B21,原材料价格表!$B$2:$J$242,9,) | D21: =VLOOKUP(B21,原材料价格表!$B$2:$G$436,2,0) | E21: =VLOOKUP(B21,原材料价格表!$B$2:$G$436,3,0) | F21: =VLOOKUP(B21,原材料价格表!$B$2:$G$436,6,0) | G21: =VLOOKUP(B21,原材料价格表!$B$2:$G$436,5,0) | H21: 0.85 | I21: =F21/G21/H21 | J21: 200 | K21: =I21*J21
B22: 售价 | D22: 128 | E22: 售卖份量/g | F22: =SUM(J21) | G22: 总成本（元） | H22: =SUM(K21) | I22: 毛利/元 | J22: =D22-H22 | K22: 毛利率 | L22: =J22/D22
A23: 黑松露和牛肉开口笑 | B23: 和牛肉糜 | C23: =VLOOKUP(B23,原材料价格表!$B$2:$J$242,9,) | D23: =VLOOKUP(B23,原材料价格表!$B$2:$G$436,2,0) | E23: =VLOOKUP(B23,原材料价格表!$B$2:$G$436,3,0) | F23: =VLOOKUP(B23,原材料价格表!$B$2:$G$436,6,0) | G23: =VLOOKUP(B23,原材料价格表!$B$2:$G$436,5,0) | H23: 1 | I23: =F23/G23/H23 | J23: 110 | K23: =I23*J23
B24: 黑松露酱 | C24: =VLOOKUP(B24,原材料价格表!$B$2:$J$242,9,) | D24: =VLOOKUP(B24,原材料价格表!$B$2:$G$436,2,0) | E24: =VLOOKUP(B24,原材料价格表!$B$2:$G$436,3,0) | F24: =VLOOKUP(B24,原材料价格表!$B$2:$G$436,6,0) | G24: =VLOOKUP(B24,原材料价格表!$B$2:$G$436,5,0) | H24: 1 | I24: =F24/G24/H24 | J24: 5 | K24: =I24*J24 | N24: =61/2
B25: 饺子皮 | C25: =VLOOKUP(B25,原材料价格表!$B$2:$J$242,9,) | D25: =VLOOKUP(B25,原材料价格表!$B$2:$G$436,2,0) | E25: =VLOOKUP(B25,原材料价格表!$B$2:$G$436,3,0) | F25: =VLOOKUP(B25,原材料价格表!$B$2:$G$436,6,0) | G25: =VLOOKUP(B25,原材料价格表!$B$2:$G$436,5,0) | H25: 1 | I25: =F25/G25/H25 | J25: 60 | K25: =I25*J25
B26: 售价 | D26: 28 | E26: 售卖份量/g | F26: =SUM(J23:J25) | G26: 总成本（元） | H26: =SUM(K23:K25) | I26: 毛利/元 | J26: =D26-H26 | K26: 毛利率 | L26: =J26/D26
A27: 黑松露和牛肉开口笑 | B27: 匙仁 | C27: =VLOOKUP(B27,原材料价格表!$B$2:$J$242,9,) | D27: =VLOOKUP(B27,原材料价格表!$B$2:$G$436,2,0) | E27: =VLOOKUP(B27,原材料价格表!$B$2:$G$436,3,0) | F27: =VLOOKUP(B27,原材料价格表!$B$2:$G$436,6,0) | G27: =VLOOKUP(B27,原材料价格表!$B$2:$G$436,5,0) | H27: 0.9 | I27: =F27/G27/H27 | J27: =110/4 | K27: =I27*J27
B28: 胸口油 | C28: =VLOOKUP(B28,原材料价格表!$B$2:$J$242,9,) | D28: =VLOOKUP(B28,原材料价格表!$B$2:$G$436,2,0) | E28: =VLOOKUP(B28,原材料价格表!$B$2:$G$436,3,0) | F28: =VLOOKUP(B28,原材料价格表!$B$2:$G$436,6,0) | G28: =VLOOKUP(B28,原材料价格表!$B$2:$G$436,5,0) | H28: 0.9 | I28: =F28/G28/H28 | J28: =110/4 | K28: =I28*J28
B29: 五花腱 | C29: =VLOOKUP(B29,原材料价格表!$B$2:$J$242,9,) | D29: =VLOOKUP(B29,原材料价格表!$B$2:$G$436,2,0) | E29: =VLOOKUP(B29,原材料价格表!$B$2:$G$436,3,0) | F29: =VLOOKUP(B29,原材料价格表!$B$2:$G$436,6,0) | G29: =VLOOKUP(B29,原材料价格表!$B$2:$G$436,5,0) | H29: 0.9 | I29: =F29/G29/H29 | J29: =110/4 | K29: =I29*J29
B30: M9和牛 | C30: =VLOOKUP(B30,原材料价格表!$B$2:$J$242,9,) | D30: =VLOOKUP(B30,原材料价格表!$B$2:$G$436,2,0) | E30: =VLOOKUP(B30,原材料价格表!$B$2:$G$436,3,0) | F30: =VLOOKUP(B30,原材料价格表!$B$2:$G$436,6,0) | G30: =VLOOKUP(B30,原材料价格表!$B$2:$G$436,5,0) | H30: 0.9 | I30: =F30/G30/H30 | J30: =110/4 | K30: =I30*J30
B31: 黑松露酱 | C31: =VLOOKUP(B31,原材料价格表!$B$2:$J$242,9,) | D31: =VLOOKUP(B31,原材料价格表!$B$2:$G$436,2,0) | E31: =VLOOKUP(B31,原材料价格表!$B$2:$G$436,3,0) | F31: =VLOOKUP(B31,原材料价格表!$B$2:$G$436,6,0) | G31: =VLOOKUP(B31,原材料价格表!$B$2:$G$436,5,0) | H31: 1 | I31: =F31/G31/H31 | J31: 5 | K31: =I31*J31
B32: 饺子皮 | C32: =VLOOKUP(B32,原材料价格表!$B$2:$J$242,9,) | D32: =VLOOKUP(B32,原材料价格表!$B$2:$G$436,2,0) | E32: =VLOOKUP(B32,原材料价格表!$B$2:$G$436,3,0) | F32: =VLOOKUP(B32,原材料价格表!$B$2:$G$436,6,0) | G32: =VLOOKUP(B32,原材料价格表!$B$2:$G$436,5,0) | H32: 1 | I32: =F32/G32/H32 | J32: 60 | K32: =I32*J32
B33: 售价 | D33: 28 | E33: 售卖份量/g | F33: =SUM(J27:J32) | G33: 总成本（元） | H33: =SUM(K27:K32) | I33: 毛利/元 | J33: =D33-H33 | K33: 毛利率 | L33: =J33/D33
A34: 贵州传统软哨 | B34: 软哨片 | C34: =VLOOKUP(B34,原材料价格表!$B$2:$J$242,9,) | D34: =VLOOKUP(B34,原材料价格表!$B$2:$G$436,2,0) | E34: =VLOOKUP(B34,原材料价格表!$B$2:$G$436,3,0) | F34: 36 | G34: =VLOOKUP(B34,原材料价格表!$B$2:$G$436,5,0) | H34: 1 | I34: =F34/G34/H34 | J34: 100 | K34: =I34*J34
B35: 芭蕉叶 | C35: =VLOOKUP(B35,原材料价格表!$B$2:$J$242,9,) | D35: =VLOOKUP(B35,原材料价格表!$B$2:$G$436,2,0) | E35: =VLOOKUP(B35,原材料价格表!$B$2:$G$436,3,0) | F35: =VLOOKUP(B35,原材料价格表!$B$2:$G$436,6,0) | G35: =VLOOKUP(B35,原材料价格表!$B$2:$G$436,5,0) | H35: 0.9 | I35: =F35/G35/H35 | J35: 5 | K35: =I35*J35
B36: 售价 | D36: 22 | E36: 售卖份量/g | F36: =SUM(J34:J35) | G36: 总成本（元） | H36: =SUM(K34:K35) | I36: 毛利/元 | J36: =D36-H36 | K36: 毛利率 | L36: =J36/D36
A37: 水晶滑肉混合物（半成品） | B37: 雪花松板肉 | C37: =VLOOKUP(B37,原材料价格表!$B$2:$J$242,9,) | D37: =VLOOKUP(B37,原材料价格表!$B$2:$G$436,2,0) | E37: =VLOOKUP(B37,原材料价格表!$B$2:$G$436,3,0) | F37: =VLOOKUP(B37,原材料价格表!$B$2:$G$436,6,0) | G37: =VLOOKUP(B37,原材料价格表!$B$2:$G$436,5,0) | H37: 1 | I37: =F37/G37/H37 | J37: 400 | K37: =I37*J37
B38: 红薯淀粉 | C38: =VLOOKUP(B38,原材料价格表!$B$2:$J$242,9,) | D38: =VLOOKUP(B38,原材料价格表!$B$2:$G$436,2,0) | E38: =VLOOKUP(B38,原材料价格表!$B$2:$G$436,3,0) | F38: =VLOOKUP(B38,原材料价格表!$B$2:$G$436,6,0) | G38: =VLOOKUP(B38,原材料价格表!$B$2:$G$436,5,0) | H38: 1 | I38: =F38/G38/H38 | J38: 150 | K38: =I38*J38
B39: 售价 | E39: 售卖份量/g | F39: 830 | G39: 总成本（元） | H39: =SUM(K37:K38) | I39: 毛利/元 | J39: =D39-H39 | K39: 毛利率 | L39: =J39/D39
A40: 手工水晶滑肉 | B40: 水晶滑肉混合物 | C40: =VLOOKUP(B40,原材料价格表!$B$2:$J$242,9,) | D40: =VLOOKUP(B40,原材料价格表!$B$2:$G$436,2,0) | E40: =VLOOKUP(B40,原材料价格表!$B$2:$G$436,3,0) | F40: =H39 | G40: =F39 | H40: 0.95 | I40: =F40/G40/H40 | J40: 200 | K40: =I40*J40
B41: 红叶生菜 | C41: =VLOOKUP(B41,原材料价格表!$B$2:$J$242,9,) | D41: =VLOOKUP(B41,原材料价格表!$B$2:$G$436,2,0) | E41: =VLOOKUP(B41,原材料价格表!$B$2:$G$436,3,0) | F41: =VLOOKUP(B41,原材料价格表!$B$2:$G$436,6,0) | G41: =VLOOKUP(B41,原材料价格表!$B$2:$G$436,5,0) | H41: 1 | I41: =F41/G41/H41 | J41: 15 | K41: =I41*J41
B42: 售价 | D42: 22 | E42: 售卖份量/g | F42: =SUM(J40:J41) | G42: 总成本（元） | H42: =SUM(K40:K41) | I42: 毛利/元 | J42: =D42-H42 | K42: 毛利率 | L42: =J42/D42
A43: 过油响皮 | B43: 猪响皮 | C43: =VLOOKUP(B43,原材料价格表!$B$2:$J$242,9,) | D43: =VLOOKUP(B43,原材料价格表!$B$2:$G$436,2,0) | E43: =VLOOKUP(B43,原材料价格表!$B$2:$G$436,3,0) | F43: =VLOOKUP(B43,原材料价格表!$B$2:$G$436,6,0) | G43: =VLOOKUP(B43,原材料价格表!$B$2:$G$436,5,0) | H43: 0.95 | I43: =F43/G43/H43 | J43: 50 | K43: =I43*J43
B44: 售价 | D44: 18 | E44: 售卖份量/g | F44: =SUM(J43) | G44: 总成本（元） | H44: =SUM(K43) | I44: 毛利/元 | J44: =D44-H44 | K44: 毛利率 | L44: =J44/D44
A45: 糯米午餐肉 | B45: 糯米午餐肉 | C45: =VLOOKUP(B45,原材料价格表!$B$2:$J$242,9,) | D45: =VLOOKUP(B45,原材料价格表!$B$2:$G$436,2,0) | E45: =VLOOKUP(B45,原材料价格表!$B$2:$G$436,3,0) | F45: =VLOOKUP(B45,原材料价格表!$B$2:$G$436,6,0) | G45: =VLOOKUP(B45,原材料价格表!$B$2:$G$436,5,0) | H45: 1 | I45: =F45/G45/H45 | J45: 170 | K45: =I45*J45
B46: 售价 | D46: 18 | E46: 售卖份量/g | F46: =SUM(J45) | G46: 总成本（元） | H46: =SUM(K45) | I46: 毛利/元 | J46: =D46-H46 | K46: 毛利率 | L46: =J46/D46
A47: 净水鲜虾 | B47: 基围虾 | C47: =VLOOKUP(B47,原材料价格表!$B$2:$J$242,9,) | D47: =VLOOKUP(B47,原材料价格表!$B$2:$G$436,2,0) | E47: =VLOOKUP(B47,原材料价格表!$B$2:$G$436,3,0) | F47: =VLOOKUP(B47,原材料价格表!$B$2:$G$436,6,0) | G47: =VLOOKUP(B47,原材料价格表!$B$2:$G$436,5,0) | H47: 1 | I47: =F47/G47/H47 | J47: 8 | K47: =I47*J47
B48: 售价 | D48: 38 | E48: 售卖份量/g | F48: =SUM(J47) | G48: 总成本（元） | H48: =SUM(K47) | I48: 毛利/元 | J48: =D48-H48 | K48: 毛利率 | L48: =J48/D48
A49: 乌鱼片 | B49: 乌鱼片 | C49: =VLOOKUP(B49,原材料价格表!$B$2:$J$242,9,) | D49: =VLOOKUP(B49,原材料价格表!$B$2:$G$436,2,0) | E49: =VLOOKUP(B49,原材料价格表!$B$2:$G$436,3,0) | F49: =VLOOKUP(B49,原材料价格表!$B$2:$G$436,6,0) | G49: =VLOOKUP(B49,原材料价格表!$B$2:$G$436,5,0) | H49: 0.95 | I49: =F49/G49/H49 | J49: 130 | K49: =I49*J49
B50: 甜菊 | C50: =VLOOKUP(B50,原材料价格表!$B$2:$J$242,9,) | D50: =VLOOKUP(B50,原材料价格表!$B$2:$G$436,2,0) | E50: =VLOOKUP(B50,原材料价格表!$B$2:$G$436,3,0) | F50: =VLOOKUP(B50,原材料价格表!$B$2:$G$436,6,0) | G50: =VLOOKUP(B50,原材料价格表!$B$2:$G$436,5,0) | H50: 0.3 | I50: =F50/G50/H50 | J50: 1.5 | K50: =I50*J50
B51: 售价 | D51: 28 | E51: 售卖份量/g | F51: =SUM(J49:J50) | G51: 总成本（元） | H51: =SUM(K49:K50) | I51: 毛利/元 | J51: =D51-H51 | K51: 毛利率 | L51: =J51/D51
A52: 海鲜拼盘 | B52: 小管 | C52: =VLOOKUP(B52,原材料价格表!$B$2:$J$242,9,) | D52: =VLOOKUP(B52,原材料价格表!$B$2:$G$436,2,0) | E52: =VLOOKUP(B52,原材料价格表!$B$2:$G$436,3,0) | F52: =VLOOKUP(B52,原材料价格表!$B$2:$G$436,6,0) | G52: =VLOOKUP(B52,原材料价格表!$B$2:$G$436,5,0) | H52: 1 | I52: =F52/G52/H52 | J52: 1 | K52: =I52*J52
B53: 10头鲍 | C53: =VLOOKUP(B53,原材料价格表!$B$2:$J$242,9,) | D53: =VLOOKUP(B53,原材料价格表!$B$2:$G$436,2,0) | E53: =VLOOKUP(B53,原材料价格表!$B$2:$G$436,3,0) | F53: =VLOOKUP(B53,原材料价格表!$B$2:$G$436,6,0) | G53: =VLOOKUP(B53,原材料价格表!$B$2:$G$436,5,0) | H53: 1 | I53: =F53/G53/H53 | J53: 3 | K53: =I53*J53
B54: 生蚝 | C54: =VLOOKUP(B54,原材料价格表!$B$2:$J$242,9,) | D54: =VLOOKUP(B54,原材料价格表!$B$2:$G$436,2,0) | E54: =VLOOKUP(B54,原材料价格表!$B$2:$G$436,3,0) | F54: =VLOOKUP(B54,原材料价格表!$B$2:$G$436,6,0) | G54: =VLOOKUP(B54,原材料价格表!$B$2:$G$436,5,0) | H54: 1 | I54: =F54/G54/H54 | J54: 2 | K54: =I54*J54
B55: 基围虾 | C55: =VLOOKUP(B55,原材料价格表!$B$2:$J$242,9,) | D55: =VLOOKUP(B55,原材料价格表!$B$2:$G$436,2,0) | E55: =VLOOKUP(B55,原材料价格表!$B$2:$G$436,3,0) | F55: =VLOOKUP(B55,原材料价格表!$B$2:$G$436,6,0) | G55: =VLOOKUP(B55,原材料价格表!$B$2:$G$436,5,0) | H55: 1 | I55: =F55/G55/H55 | J55: 4 | K55: =I55*J55
B56: 紫苏叶 | C56: =VLOOKUP(B56,原材料价格表!$B$2:$J$242,9,) | D56: =VLOOKUP(B56,原材料价格表!$B$2:$G$436,2,0) | E56: =VLOOKUP(B56,原材料价格表!$B$2:$G$436,3,0) | F56: =VLOOKUP(B56,原材料价格表!$B$2:$G$436,6,0) | G56: =VLOOKUP(B56,原材料价格表!$B$2:$G$436,5,0) | H56: 1 | I56: =F56/G56/H56 | J56: 2 | K56: =I56*J56
B57: 售价 | D57: 68 | E57: 售卖份量/g | F57: =SUM(J52:J56) | G57: 总成本（元） | H57: =SUM(K52:K56) | I57: 毛利/元 | J57: =D57-H57 | K57: 毛利率 | L57: =J57/D57
A58: 黑金虾滑 | B58: 虾滑 | C58: =VLOOKUP(B58,原材料价格表!$B$2:$J$242,9,) | D58: =VLOOKUP(B58,原材料价格表!$B$2:$G$436,2,0) | E58: =VLOOKUP(B58,原材料价格表!$B$2:$G$436,3,0) | F58: =VLOOKUP(B58,原材料价格表!$B$2:$G$436,6,0) | G58: =VLOOKUP(B58,原材料价格表!$B$2:$G$436,5,0) | H58: 1 | I58: =F58/G58/H58 | J58: 150 | K58: =I58*J58
B59: 墨鱼汁 | C59: =VLOOKUP(B59,原材料价格表!$B$2:$J$242,9,) | D59: =VLOOKUP(B59,原材料价格表!$B$2:$G$436,2,0) | E59: =VLOOKUP(B59,原材料价格表!$B$2:$G$436,3,0) | F59: =VLOOKUP(B59,原材料价格表!$B$2:$G$436,6,0) | G59: =VLOOKUP(B59,原材料价格表!$B$2:$G$436,5,0) | H59: 1 | I59: =F59/G59/H59 | J59: 1 | K59: =I59*J59
B60: 金蒜酥 | C60: =VLOOKUP(B60,原材料价格表!$B$2:$J$242,9,) | D60: =VLOOKUP(B60,原材料价格表!$B$2:$G$436,2,0) | E60: =VLOOKUP(B60,原材料价格表!$B$2:$G$436,3,0) | F60: =VLOOKUP(B60,原材料价格表!$B$2:$G$436,6,0) | G60: =VLOOKUP(B60,原材料价格表!$B$2:$G$436,5,0) | H60: 2 | I60: =F60/G60/H60 | J60: 1 | K60: =I60*J60
B61: 芭蕉叶 | C61: =VLOOKUP(B61,原材料价格表!$B$2:$J$242,9,) | D61: =VLOOKUP(B61,原材料价格表!$B$2:$G$436,2,0) | E61: =VLOOKUP(B61,原材料价格表!$B$2:$G$436,3,0) | F61: =VLOOKUP(B61,原材料价格表!$B$2:$G$436,6,0) | G61: =VLOOKUP(B61,原材料价格表!$B$2:$G$436,5,0) | H61: 0.9 | I61: =F61/G61/H61 | J61: 5 | K61: =I61*J61
B62: 售价 | D62: 38 | E62: 售卖份量/g | F62: =SUM(J58:J61) | G62: 总成本（元） | H62: =SUM(K58:K61) | I62: 毛利/元 | J62: =D62-H62 | K62: 毛利率 | L62: =J62/D62
A63: 鲜板栗 | B63: 鲜板栗 | C63: =VLOOKUP(B63,原材料价格表!$B$2:$J$242,9,) | D63: =VLOOKUP(B63,原材料价格表!$B$2:$G$436,2,0) | E63: =VLOOKUP(B63,原材料价格表!$B$2:$G$436,3,0) | F63: =VLOOKUP(B63,原材料价格表!$B$2:$G$436,6,0) | G63: =VLOOKUP(B63,原材料价格表!$B$2:$G$436,5,0) | H63: 1 | I63: =F63/G63/H63 | J63: 130 | K63: =I63*J63
B64: 羽衣甘蓝 | C64: =VLOOKUP(B64,原材料价格表!$B$2:$J$242,9,) | D64: =VLOOKUP(B64,原材料价格表!$B$2:$G$436,2,0) | E64: =VLOOKUP(B64,原材料价格表!$B$2:$G$436,3,0) | F64: =VLOOKUP(B64,原材料价格表!$B$2:$G$436,6,0) | G64: =VLOOKUP(B64,原材料价格表!$B$2:$G$436,5,0) | H64: 1 | I64: =F64/G64/H64 | J64: 15 | K64: =I64*J64
B65: 售价 | D65: 16 | E65: 售卖份量/g | F65: =SUM(J63:J64) | G65: 总成本（元） | H65: =SUM(K63:K64) | I65: 毛利/元 | J65: =D65-H65 | K65: 毛利率 | L65: =J65/D65
A66: 鲜百合 | B66: 鲜百合 | C66: =VLOOKUP(B66,原材料价格表!$B$2:$J$242,9,) | D66: =VLOOKUP(B66,原材料价格表!$B$2:$G$436,2,0) | E66: =VLOOKUP(B66,原材料价格表!$B$2:$G$436,3,0) | F66: =VLOOKUP(B66,原材料价格表!$B$2:$G$436,6,0) | G66: =VLOOKUP(B66,原材料价格表!$B$2:$G$436,5,0) | H66: 0.9 | I66: =F66/G66/H66 | J66: 50 | K66: =I66*J66
B67: 售价 | D67: 22 | E67: 售卖份量/g | F67: =SUM(J66) | G67: 总成本（元） | H67: =SUM(K66) | I67: 毛利/元 | J67: =D67-H67 | K67: 毛利率 | L67: =J67/D67
A68: 血皮菜 | B68: 血皮菜 | C68: =VLOOKUP(B68,原材料价格表!$B$2:$J$242,9,) | D68: =VLOOKUP(B68,原材料价格表!$B$2:$G$436,2,0) | E68: =VLOOKUP(B68,原材料价格表!$B$2:$G$436,3,0) | F68: =VLOOKUP(B68,原材料价格表!$B$2:$G$436,6,0) | G68: =VLOOKUP(B68,原材料价格表!$B$2:$G$436,5,0) | H68: 0.9 | I68: =F68/G68/H68 | J68: 130 | K68: =I68*J68
B69: 售价 | D69: 16 | E69: 售卖份量/g | F69: =SUM(J68) | G69: 总成本（元） | H69: =SUM(K68) | I69: 毛利/元 | J69: =D69-H69 | K69: 毛利率 | L69: =J69/D69
A70: 鲜黄花 | B70: 鲜黄花 | C70: =VLOOKUP(B70,原材料价格表!$B$2:$J$242,9,) | D70: =VLOOKUP(B70,原材料价格表!$B$2:$G$436,2,0) | E70: =VLOOKUP(B70,原材料价格表!$B$2:$G$436,3,0) | F70: =VLOOKUP(B70,原材料价格表!$B$2:$G$436,6,0) | G70: =VLOOKUP(B70,原材料价格表!$B$2:$G$436,5,0) | H70: 0.9 | I70: =F70/G70/H70 | J70: 60 | K70: =I70*J70
B71: 红叶生菜 | C71: =VLOOKUP(B71,原材料价格表!$B$2:$J$242,9,) | D71: =VLOOKUP(B71,原材料价格表!$B$2:$G$436,2,0) | E71: =VLOOKUP(B71,原材料价格表!$B$2:$G$436,3,0) | F71: =VLOOKUP(B71,原材料价格表!$B$2:$G$436,6,0) | G71: =VLOOKUP(B71,原材料价格表!$B$2:$G$436,5,0) | H71: 0.85 | I71: =F71/G71/H71 | J71: 30 | K71: =I71*J71
B72: 售价 | D72: 16 | E72: 售卖份量/g | F72: =SUM(J70:J71) | G72: 总成本（元） | H72: =SUM(K70:K71) | I72: 毛利/元 | J72: =D72-H72 | K72: 毛利率 | L72: =J72/D72
A73: 山药 | B73: 粗山药 | C73: =VLOOKUP(B73,原材料价格表!$B$2:$J$242,9,) | D73: =VLOOKUP(B73,原材料价格表!$B$2:$G$436,2,0) | E73: =VLOOKUP(B73,原材料价格表!$B$2:$G$436,3,0) | F73: =VLOOKUP(B73,原材料价格表!$B$2:$G$436,6,0) | G73: =VLOOKUP(B73,原材料价格表!$B$2:$G$436,5,0) | H73: 0.9 | I73: =F73/G73/H73 | J73: 160 | K73: =I73*J73
B74: 甜菊 | C74: =VLOOKUP(B74,原材料价格表!$B$2:$J$242,9,) | D74: =VLOOKUP(B74,原材料价格表!$B$2:$G$436,2,0) | E74: =VLOOKUP(B74,原材料价格表!$B$2:$G$436,3,0) | F74: =VLOOKUP(B74,原材料价格表!$B$2:$G$436,6,0) | G74: =VLOOKUP(B74,原材料价格表!$B$2:$G$436,5,0) | H74: 0.3 | I74: =F74/G74/H74 | J74: 1.5 | K74: =I74*J74
B75: 售价 | D75: 12 | E75: 售卖份量/g | F75: =SUM(J73:J74) | G75: 总成本（元） | H75: =SUM(K73:K74) | I75: 毛利/元 | J75: =D75-H75 | K75: 毛利率 | L75: =J75/D75
A76: 甜笋（刺身级） | B76: 甜笋 | C76: =VLOOKUP(B76,原材料价格表!$B$2:$J$242,9,) | D76: =VLOOKUP(B76,原材料价格表!$B$2:$G$436,2,0) | E76: =VLOOKUP(B76,原材料价格表!$B$2:$G$436,3,0) | F76: =VLOOKUP(B76,原材料价格表!$B$2:$G$436,6,0) | G76: =VLOOKUP(B76,原材料价格表!$B$2:$G$436,5,0) | H76: 0.9 | I76: =F76/G76/H76 | J76: 80 | K76: =I76*J76
B77: 水 | C77: =VLOOKUP(B77,原材料价格表!$B$2:$J$242,9,) | D77: =VLOOKUP(B77,原材料价格表!$B$2:$G$436,2,0) | E77: =VLOOKUP(B77,原材料价格表!$B$2:$G$436,3,0) | F77: =VLOOKUP(B77,原材料价格表!$B$2:$G$436,6,0) | G77: =VLOOKUP(B77,原材料价格表!$B$2:$G$436,5,0) | H77: 1 | I77: =F77/G77/H77 | J77: 80 | K77: =I77*J77
B78: 售价 | D78: 16 | E78: 售卖份量/g | F78: =SUM(J76:J77) | G78: 总成本（元） | H78: =SUM(K76:K77) | I78: 毛利/元 | J78: =D78-H78 | K78: 毛利率 | L78: =J78/D78
A79: 三脆碗 | B79: 干黄花 | C79: =VLOOKUP(B79,原材料价格表!$B$2:$J$242,9,) | D79: =VLOOKUP(B79,原材料价格表!$B$2:$G$436,2,0) | E79: =VLOOKUP(B79,原材料价格表!$B$2:$G$436,3,0) | F79: =VLOOKUP(B79,原材料价格表!$B$2:$G$436,6,0) | G79: =VLOOKUP(B79,原材料价格表!$B$2:$G$436,5,0) | H79: 1 | I79: =F79/G79/H79 | J79: 25 | K79: =I79*J79
B80: 干花菜 | C80: =VLOOKUP(B80,原材料价格表!$B$2:$J$242,9,) | D80: =VLOOKUP(B80,原材料价格表!$B$2:$G$436,2,0) | E80: =VLOOKUP(B80,原材料价格表!$B$2:$G$436,3,0) | F80: =VLOOKUP(B80,原材料价格表!$B$2:$G$436,6,0) | G80: =VLOOKUP(B80,原材料价格表!$B$2:$G$436,5,0) | H80: 1 | I80: =F80/G80/H80 | J80: 50 | K80: =I80*J80
B81: 干贡菜 | C81: =VLOOKUP(B81,原材料价格表!$B$2:$J$242,9,) | D81: =VLOOKUP(B81,原材料价格表!$B$2:$G$436,2,0) | E81: =VLOOKUP(B81,原材料价格表!$B$2:$G$436,3,0) | F81: =VLOOKUP(B81,原材料价格表!$B$2:$G$436,6,0) | G81: =VLOOKUP(B81,原材料价格表!$B$2:$G$436,5,0) | H81: 1 | I81: =F81/G81/H81 | J81: 40 | K81: =I81*J81
B82: 售价 | D82: 22 | E82: 售卖份量/g | F82: =SUM(J79:J81) | G82: 总成本（元） | H82: =SUM(K79:K81) | I82: 毛利/元 | J82: =D82-H82 | K82: 毛利率 | L82: =J82/D82
A83: 姜柄瓜 | B83: 姜柄瓜 | C83: =VLOOKUP(B83,原材料价格表!$B$2:$J$242,9,) | D83: =VLOOKUP(B83,原材料价格表!$B$2:$G$436,2,0) | E83: =VLOOKUP(B83,原材料价格表!$B$2:$G$436,3,0) | F83: =VLOOKUP(B83,原材料价格表!$B$2:$G$436,6,0) | G83: =VLOOKUP(B83,原材料价格表!$B$2:$G$436,5,0) | H83: 0.95 | I83: =F83/G83/H83 | J83: 140 | K83: =I83*J83
B84: 羽衣甘蓝 | C84: =VLOOKUP(B84,原材料价格表!$B$2:$J$242,9,) | D84: =VLOOKUP(B84,原材料价格表!$B$2:$G$436,2,0) | E84: =VLOOKUP(B84,原材料价格表!$B$2:$G$436,3,0) | F84: =VLOOKUP(B84,原材料价格表!$B$2:$G$436,6,0) | G84: =VLOOKUP(B84,原材料价格表!$B$2:$G$436,5,0) | H84: 1 | I84: =F84/G84/H84 | J84: 20 | K84: =I84*J84
B85: 售价 | D85: 16 | E85: 售卖份量/g | F85: =SUM(J83:J84) | G85: 总成本（元） | H85: =SUM(K83:K84) | I85: 毛利/元 | J85: =D85-H85 | K85: 毛利率 | L85: =J85/D85
A86: 双花碗 | B86: 花生芽 | C86: =VLOOKUP(B86,原材料价格表!$B$2:$J$242,9,) | D86: =VLOOKUP(B86,原材料价格表!$B$2:$G$436,2,0) | E86: =VLOOKUP(B86,原材料价格表!$B$2:$G$436,3,0) | F86: =VLOOKUP(B86,原材料价格表!$B$2:$G$436,6,0) | G86: =VLOOKUP(B86,原材料价格表!$B$2:$G$436,5,0) | H86: 0.95 | I86: =F86/G86/H86 | J86: 120 | K86: =I86*J86
B87: 黄瓜花 | C87: =VLOOKUP(B87,原材料价格表!$B$2:$J$242,9,) | D87: =VLOOKUP(B87,原材料价格表!$B$2:$G$436,2,0) | E87: =VLOOKUP(B87,原材料价格表!$B$2:$G$436,3,0) | F87: =VLOOKUP(B87,原材料价格表!$B$2:$G$436,6,0) | G87: =VLOOKUP(B87,原材料价格表!$B$2:$G$436,5,0) | H87: 0.9 | I87: =F87/G87/H87 | J87: 50 | K87: =I87*J87
B88: 售价 | D88: 22 | E88: 售卖份量/g | F88: =SUM(J86:J87) | G88: 总成本（元） | H88: =SUM(K86:K87) | I88: 毛利/元 | J88: =D88-H88 | K88: 毛利率 | L88: =J88/D88
A89: 彩云土豆 | B89: 七彩土豆 | C89: =VLOOKUP(B89,原材料价格表!$B$2:$J$242,9,) | D89: =VLOOKUP(B89,原材料价格表!$B$2:$G$436,2,0) | E89: =VLOOKUP(B89,原材料价格表!$B$2:$G$436,3,0) | F89: =VLOOKUP(B89,原材料价格表!$B$2:$G$436,6,0) | G89: =VLOOKUP(B89,原材料价格表!$B$2:$G$436,5,0) | H89: 0.9 | I89: =F89/G89/H89 | J89: 100 | K89: =I89*J89
B90: 售价 | D90: 12 | E90: 售卖份量/g | F90: =SUM(J89) | G90: 总成本（元） | H90: =SUM(K89) | I90: 毛利/元 | J90: =D90-H90 | K90: 毛利率 | L90: =J90/D90
A91: 藕 | B91: 藕 | C91: =VLOOKUP(B91,原材料价格表!$B$2:$J$242,9,) | D91: =VLOOKUP(B91,原材料价格表!$B$2:$G$436,2,0) | E91: =VLOOKUP(B91,原材料价格表!$B$2:$G$436,3,0) | F91: =VLOOKUP(B91,原材料价格表!$B$2:$G$436,6,0) | G91: =VLOOKUP(B91,原材料价格表!$B$2:$G$436,5,0) | H91: 0.9 | I91: =F91/G91/H91 | J91: 120 | K91: =I91*J91
B92: 红叶生菜 | C92: =VLOOKUP(B92,原材料价格表!$B$2:$J$242,9,) | D92: =VLOOKUP(B92,原材料价格表!$B$2:$G$436,2,0) | E92: =VLOOKUP(B92,原材料价格表!$B$2:$G$436,3,0) | F92: =VLOOKUP(B92,原材料价格表!$B$2:$G$436,6,0) | G92: =VLOOKUP(B92,原材料价格表!$B$2:$G$436,5,0) | H92: 0.85 | I92: =F92/G92/H92 | J92: 25 | K92: =I92*J92
B93: 羽衣甘蓝 | C93: =VLOOKUP(B93,原材料价格表!$B$2:$J$242,9,) | D93: =VLOOKUP(B93,原材料价格表!$B$2:$G$436,2,0) | E93: =VLOOKUP(B93,原材料价格表!$B$2:$G$436,3,0) | F93: =VLOOKUP(B93,原材料价格表!$B$2:$G$436,6,0) | G93: =VLOOKUP(B93,原材料价格表!$B$2:$G$436,5,0) | H93: 1 | I93: =F93/G93/H93 | J93: 25 | K93: =I93*J93
B94: 售价 | D94: 12 | E94: 售卖份量/g | F94: =SUM(J91:J93) | G94: 总成本（元） | H94: =SUM(K91:K93) | I94: 毛利/元 | J94: =D94-H94 | K94: 毛利率 | L94: =J94/D94
A95: 石磨黑豆腐 | B95: 黑豆腐 | C95: =VLOOKUP(B95,原材料价格表!$B$2:$J$242,9,) | D95: =VLOOKUP(B95,原材料价格表!$B$2:$G$436,2,0) | E95: =VLOOKUP(B95,原材料价格表!$B$2:$G$436,3,0) | F95: =VLOOKUP(B95,原材料价格表!$B$2:$G$436,6,0) | G95: =VLOOKUP(B95,原材料价格表!$B$2:$G$436,5,0) | H95: 1 | I95: =F95/G95/H95 | J95: 250 | K95: =I95*J95
B96: 红叶生菜 | C96: =VLOOKUP(B96,原材料价格表!$B$2:$J$242,9,) | D96: =VLOOKUP(B96,原材料价格表!$B$2:$G$436,2,0) | E96: =VLOOKUP(B96,原材料价格表!$B$2:$G$436,3,0) | F96: =VLOOKUP(B96,原材料价格表!$B$2:$G$436,6,0) | G96: =VLOOKUP(B96,原材料价格表!$B$2:$G$436,5,0) | H96: 0.85 | I96: =F96/G96/H96 | J96: 30 | K96: =I96*J96
B97: 售价 | D97: 16 | E97: 售卖份量/g | F97: =SUM(J95:J96) | G97: 总成本（元） | H97: =SUM(K95:K96) | I97: 毛利/元 | J97: =D97-H97 | K97: 毛利率 | L97: =J97/D97
A98: 野篮子菌菇组合 | B98: 牛肝菌 | C98: =VLOOKUP(B98,原材料价格表!$B$2:$J$242,9,) | D98: =VLOOKUP(B98,原材料价格表!$B$2:$G$436,2,0) | E98: =VLOOKUP(B98,原材料价格表!$B$2:$G$436,3,0) | F98: =VLOOKUP(B98,原材料价格表!$B$2:$G$436,6,0) | G98: =VLOOKUP(B98,原材料价格表!$B$2:$G$436,5,0) | H98: 0.95 | I98: =F98/G98/H98 | J98: 50 | K98: =I98*J98
B99: 球盖菇 | C99: =VLOOKUP(B99,原材料价格表!$B$2:$J$242,9,) | D99: =VLOOKUP(B99,原材料价格表!$B$2:$G$436,2,0) | E99: =VLOOKUP(B99,原材料价格表!$B$2:$G$436,3,0) | F99: =VLOOKUP(B99,原材料价格表!$B$2:$G$436,6,0) | G99: =VLOOKUP(B99,原材料价格表!$B$2:$G$436,5,0) | H99: 0.95 | I99: =F99/G99/H99 | J99: 50 | K99: =I99*J99
B100: 鹿茸菇 | C100: =VLOOKUP(B100,原材料价格表!$B$2:$J$242,9,) | D100: =VLOOKUP(B100,原材料价格表!$B$2:$G$436,2,0) | E100: =VLOOKUP(B100,原材料价格表!$B$2:$G$436,3,0) | F100: =VLOOKUP(B100,原材料价格表!$B$2:$G$436,6,0) | G100: =VLOOKUP(B100,原材料价格表!$B$2:$G$436,5,0) | H100: 0.95 | I100: =F100/G100/H100 | J100: 60 | K100: =I100*J100
...

Sheet 糖水铺
A1: 菜品成本卡
A2: 菜品 | B2: 名称 | C2: 进货渠道 | D2: 品牌 | E2: 进价/元 | F2: 进货量/g | G2: 净货率 | H2: 单价/g | I2: 用量/g | J2: 成本/元 | K2: 备注
A3: 山茶花茶汤（半成品） | B3: 山茶花乌龙茶 | C3: =VLOOKUP(B3,原材料价格表!$B$2:$G$436,2,0) | D3: =VLOOKUP(B3,原材料价格表!$B$2:$G$436,4,0) | E3: =VLOOKUP(B3,原材料价格表!$B$2:$G$436,6,0) | F3: =VLOOKUP(B3,原材料价格表!$B$2:$G$436,5,0) | G3: 1 | H3: =E3/F3/G3 | I3: 30 | J3: =H3*I3
B4: 水 | C4: =VLOOKUP(B4,原材料价格表!$B$2:$G$436,2,0) | D4: =VLOOKUP(B4,原材料价格表!$B$2:$G$436,4,0) | E4: =VLOOKUP(B4,原材料价格表!$B$2:$G$436,6,0) | F4: =VLOOKUP(B4,原材料价格表!$B$2:$G$436,5,0) | G4: 1 | H4: =E4/F4/G4 | I4: 700 | J4: =H4*I4
B5: 冰块 | C5: =VLOOKUP(B5,原材料价格表!$B$2:$G$436,2,0) | D5: =VLOOKUP(B5,原材料价格表!$B$2:$G$436,4,0) | E5: =VLOOKUP(B5,原材料价格表!$B$2:$G$436,6,0) | F5: =VLOOKUP(B5,原材料价格表!$B$2:$G$436,5,0) | G5: 1 | H5: =E5/F5/G5 | I5: 50 | J5: =H5*I5
B6: 冰块 | C6: =VLOOKUP(B6,原材料价格表!$B$2:$G$436,2,0) | D6: =VLOOKUP(B6,原材料价格表!$B$2:$G$436,4,0) | E6: =VLOOKUP(B6,原材料价格表!$B$2:$G$436,6,0) | F6: =VLOOKUP(B6,原材料价格表!$B$2:$G$436,5,0) | G6: 1 | H6: =E6/F6/G6 | I6: 500 | J6: =H6*I6
B7: 售价 | D7: 售卖份量/g | E7: =SUM(I3:I6)-30 | F7: 总成本（元） | G7: =SUM(J3:J6) | H7: 毛利/元 | I7: =C7-G7 | J7: 毛利率 | K7: =I7/C7
A8: 野刺梨山茶 | B8: 刺梨原浆 | C8: =VLOOKUP(B8,原材料价格表!$B$2:$G$436,2,0) | D8: =VLOOKUP(B8,原材料价格表!$B$2:$G$436,4,0) | E8: =VLOOKUP(B8,原材料价格表!$B$2:$G$436,6,0) | F8: =VLOOKUP(B8,原材料价格表!$B$2:$G$436,5,0) | G8: 1 | H8: =E8/F8/G8 | I8: 100 | J8: =H8*I8
B9: 山茶花茶汤 | C9: =VLOOKUP(B9,原材料价格表!$B$2:$G$436,2,0) | D9: =VLOOKUP(B9,原材料价格表!$B$2:$G$436,4,0) | E9: =VLOOKUP(B9,原材料价格表!$B$2:$G$436,6,0) | F9: =VLOOKUP(B9,原材料价格表!$B$2:$G$436,5,0) | G9: 1 | H9: =E9/F9/G9 | I9: 150 | J9: =H9*I9
B10: 果葡糖浆 | C10: =VLOOKUP(B10,原材料价格表!$B$2:$G$436,2,0) | D10: =VLOOKUP(B10,原材料价格表!$B$2:$G$436,4,0) | E10: =VLOOKUP(B10,原材料价格表!$B$2:$G$436,6,0) | F10: =VLOOKUP(B10,原材料价格表!$B$2:$G$436,5,0) | G10: 1 | H10: =E10/F10/G10 | I10: 50 | J10: =H10*I10
B11: 冰块 | C11: =VLOOKUP(B11,原材料价格表!$B$2:$G$436,2,0) | D11: =VLOOKUP(B11,原材料价格表!$B$2:$G$436,4,0) | E11: =VLOOKUP(B11,原材料价格表!$B$2:$G$436,6,0) | F11: =VLOOKUP(B11,原材料价格表!$B$2:$G$436,5,0) | G11: 1 | H11: =E11/F11/G11 | I11: 200 | J11: =H11*I11
B12: 刺梨果干 | C12: =VLOOKUP(B12,原材料价格表!$B$2:$G$436,2,0) | D12: =VLOOKUP(B12,原材料价格表!$B$2:$G$436,4,0) | E12: =VLOOKUP(B12,原材料价格表!$B$2:$G$436,6,0) | F12: =VLOOKUP(B12,原材料价格表!$B$2:$G$436,5,0) | G12: 1 | H12: =E12/F12/G12 | I12: 30 | J12: =H12*I12
B13: 售价 | C13: 18 | D13: 售卖份量/g | E13: =SUM(I8:I12) | F13: 总成本（元） | G13: =SUM(J8:J12) | H13: 毛利/元 | I13: =C13-G13 | J13: 毛利率 | K13: =I13/C13
A14: 五指毛桃茶汤（半成品） | B14: 五指毛桃茶包 | C14: =VLOOKUP(B14,原材料价格表!$B$2:$G$436,2,0) | D14: =VLOOKUP(B14,原材料价格表!$B$2:$G$436,3,0) | E14: =VLOOKUP(B14,原材料价格表!$B$2:$G$436,6,0) | F14: =VLOOKUP(B14,原材料价格表!$B$2:$G$436,5,0) | G14: 1 | H14: =E14/F14/G14 | I14: 2 | J14: =H14*I14
B15: 水 | C15: =VLOOKUP(B15,原材料价格表!$B$2:$G$436,2,0) | D15: =VLOOKUP(B15,原材料价格表!$B$2:$G$436,3,0) | E15: =VLOOKUP(B15,原材料价格表!$B$2:$G$436,6,0) | F15: =VLOOKUP(B15,原材料价格表!$B$2:$G$436,5,0) | G15: 1 | H15: =E15/F15/G15 | I15: 1000 | J15: =H15*I15
B16: 果葡糖浆 | C16: =VLOOKUP(B16,原材料价格表!$B$2:$G$436,2,0) | D16: =VLOOKUP(B16,原材料价格表!$B$2:$G$436,3,0) | E16: =VLOOKUP(B16,原材料价格表!$B$2:$G$436,6,0) | F16: =VLOOKUP(B16,原材料价格表!$B$2:$G$436,5,0) | G16: 1 | H16: =E16/F16/G16 | I16: 35 | J16: =H16*I16
B17: 售价 | D17: 售卖份量/g | E17: =SUM(I14:I16)-2 | F17: 总成本（元） | G17: =SUM(J14:J16) | H17: 毛利/元 | I17: =C17-G17 | J17: 毛利率 | K17: =I17/C17
A18: 五指毛桃山茶 | B18: 五指毛桃茶汤 | C18: =VLOOKUP(B18,原材料价格表!$B$2:$G$436,2,0) | D18: =VLOOKUP(B18,原材料价格表!$B$2:$G$436,3,0) | E18: =VLOOKUP(B18,原材料价格表!$B$2:$G$436,6,0) | F18: =VLOOKUP(B18,原材料价格表!$B$2:$G$436,5,0) | G18: 1 | H18: =E18/F18/G18 | I18: 200 | J18: =H18*I18
B19: 薏仁罐头 | C19: =VLOOKUP(B19,原材料价格表!$B$2:$G$436,2,0) | D19: =VLOOKUP(B19,原材料价格表!$B$2:$G$436,3,0) | E19: =VLOOKUP(B19,原材料价格表!$B$2:$G$436,6,0) | F19: =VLOOKUP(B19,原材料价格表!$B$2:$G$436,5,0) | G19: 1 | H19: =E19/F19/G19 | I19: 40 | J19: =H19*I19
B20: 果葡糖浆 | C20: =VLOOKUP(B20,原材料价格表!$B$2:$G$436,2,0) | D20: =VLOOKUP(B20,原材料价格表!$B$2:$G$436,3,0) | E20: =VLOOKUP(B20,原材料价格表!$B$2:$G$436,6,0) | F20: =VLOOKUP(B20,原材料价格表!$B$2:$G$436,5,0) | G20: 1 | H20: =E20/F20/G20 | I20: 10 | J20: =H20*I20
B21: 冰块 | C21: =VLOOKUP(B21,原材料价格表!$B$2:$G$436,2,0) | D21: =VLOOKUP(B21,原材料价格表!$B$2:$G$436,3,0) | E21: =VLOOKUP(B21,原材料价格表!$B$2:$G$436,6,0) | F21: =VLOOKUP(B21,原材料价格表!$B$2:$G$436,5,0) | G21: 1 | H21: =E21/F21/G21 | I21: 250 | J21: =H21*I21
B22: 五指毛桃干 | C22: =VLOOKUP(B22,原材料价格表!$B$2:$G$436,2,0) | D22: =VLOOKUP(B22,原材料价格表!$B$2:$G$436,3,0) | E22: =VLOOKUP(B22,原材料价格表!$B$2:$G$436,6,0) | F22: =VLOOKUP(B22,原材料价格表!$B$2:$G$436,5,0) | G22: 1 | H22: =E22/F22/G22 | I22: 10 | J22: =H22*I22
B23: 售价 | C23: 18 | D23: 售卖份量/g | E23: =SUM(I18:I22) | F23: 总成本（元） | G23: =SUM(J18:J22) | H23: 毛利/元 | I23: =C23-G23 | J23: 毛利率 | K23: =I23/C23
A24: 鸭屎香乌龙茶汤（半成品） | B24: 鸭屎香乌龙茶茶叶 | C24: =VLOOKUP(B24,原材料价格表!$B$2:$G$436,2,0) | D24: =VLOOKUP(B24,原材料价格表!$B$2:$G$436,4,0) | E24: =VLOOKUP(B24,原材料价格表!$B$2:$G$436,6,0) | F24: =VLOOKUP(B24,原材料价格表!$B$2:$G$436,5,0) | G24: 1 | H24: =E24/F24/G24 | I24: 30 | J24: =H24*I24
B25: 水 | C25: =VLOOKUP(B25,原材料价格表!$B$2:$G$436,2,0) | D25: =VLOOKUP(B25,原材料价格表!$B$2:$G$436,4,0) | E25: =VLOOKUP(B25,原材料价格表!$B$2:$G$436,6,0) | F25: =VLOOKUP(B25,原材料价格表!$B$2:$G$436,5,0) | G25: 1 | H25: =E25/F25/G25 | I25: 1800 | J25: =H25*I25
B26: 售价 | D26: 售卖份量/g | E26: =SUM(I24:I25)-30 | F26: 总成本（元） | G26: =SUM(J24:J25) | H26: 毛利/元 | I26: =C26-G26 | J26: 毛利率 | K26: =I26/C26
A27: 柠檬山茶 | B27: 香水柠檬 | C27: =VLOOKUP(B27,原材料价格表!$B$2:$G$436,2,0) | D27: =VLOOKUP(B27,原材料价格表!$B$2:$G$436,4,0) | E27: =VLOOKUP(B27,原材料价格表!$B$2:$G$436,6,0) | F27: =VLOOKUP(B27,原材料价格表!$B$2:$G$436,5,0) | G27: 0.85 | H27: =E27/F27/G27 | I27: 30 | J27: =H27*I27
B28: 鸭屎香乌龙茶汤 | C28: =VLOOKUP(B28,原材料价格表!$B$2:$G$436,2,0) | D28: =VLOOKUP(B28,原材料价格表!$B$2:$G$436,4,0) | E28: =VLOOKUP(B28,原材料价格表!$B$2:$G$436,6,0) | F28: =VLOOKUP(B28,原材料价格表!$B$2:$G$436,5,0) | G28: 1 | H28: =E28/F28/G28 | I28: 200 | J28: =H28*I28
B29: 果葡糖浆 | C29: =VLOOKUP(B29,原材料价格表!$B$2:$G$436,2,0) | D29: =VLOOKUP(B29,原材料价格表!$B$2:$G$436,4,0) | E29: =VLOOKUP(B29,原材料价格表!$B$2:$G$436,6,0) | F29: =VLOOKUP(B29,原材料价格表!$B$2:$G$436,5,0) | G29: 1 | H29: =E29/F29/G29 | I29: 40 | J29: =H29*I29
B30: 香水柠檬 | C30: =VLOOKUP(B30,原材料价格表!$B$2:$G$436,2,0) | D30: =VLOOKUP(B30,原材料价格表!$B$2:$G$436,4,0) | E30: =VLOOKUP(B30,原材料价格表!$B$2:$G$436,6,0) | F30: =VLOOKUP(B30,原材料价格表!$B$2:$G$436,5,0) | G30: 0.85 | H30: =E30/F30/G30 | I30: 30 | J30: =H30*I30
B31: 黄柠檬 | C31: =VLOOKUP(B31,原材料价格表!$B$2:$G$436,2,0) | D31: =VLOOKUP(B31,原材料价格表!$B$2:$G$436,4,0) | E31: =VLOOKUP(B31,原材料价格表!$B$2:$G$436,6,0) | F31: =VLOOKUP(B31,原材料价格表!$B$2:$G$436,5,0) | G31: 0.85 | H31: =E31/F31/G31 | I31: 15 | J31: =H31*I31
B32: 售价 | C32: 18 | D32: 售卖份量/g | E32: =SUM(I27:I31) | F32: 总成本（元） | G32: =SUM(J27:J31) | H32: 毛利/元 | I32: =C32-G32 | J32: 毛利率 | K32: =I32/C32
A33: 雪域藏茶茶汤（半成品） | B33: 雪域藏茶 | C33: =VLOOKUP(B33,原材料价格表!$B$2:$G$436,2,0) | D33: =VLOOKUP(B33,原材料价格表!$B$2:$G$436,4,0) | E33: =VLOOKUP(B33,原材料价格表!$B$2:$G$436,6,0) | F33: =VLOOKUP(B33,原材料价格表!$B$2:$G$436,5,0) | G33: 1 | H33: =E33/F33/G33 | I33: 50 | J33: =H33*I33
B34: 水 | C34: =VLOOKUP(B34,原材料价格表!$B$2:$G$436,2,0) | D34: =VLOOKUP(B34,原材料价格表!$B$2:$G$436,4,0) | E34: =VLOOKUP(B34,原材料价格表!$B$2:$G$436,6,0) | F34: =VLOOKUP(B34,原材料价格表!$B$2:$G$436,5,0) | G34: 1 | H34: =E34/F34/G34 | I34: 1500 | J34: =H34*I34
B35: 售价 | D35: 售卖份量/g | E35: 1500 | F35: 总成本（元） | G35: =SUM(J33:J34) | H35: 毛利/元 | I35: =C35-G35 | J35: 毛利率 | K35: =I35/C35
A36: 柠檬藏茶 | B36: 香水柠檬 | C36: =VLOOKUP(B36,原材料价格表!$B$2:$G$436,2,0) | D36: =VLOOKUP(B36,原材料价格表!$B$2:$G$436,4,0) | E36: =VLOOKUP(B36,原材料价格表!$B$2:$G$436,6,0) | F36: =VLOOKUP(B36,原材料价格表!$B$2:$G$436,5,0) | G36: 0.85 | H36: =E36/F36/G36 | I36: 40 | J36: =H36*I36
B37: 蔗糖糖浆 | C37: =VLOOKUP(B37,原材料价格表!$B$2:$G$436,2,0) | D37: =VLOOKUP(B37,原材料价格表!$B$2:$G$436,4,0) | E37: =VLOOKUP(B37,原材料价格表!$B$2:$G$436,6,0) | F37: =VLOOKUP(B37,原材料价格表!$B$2:$G$436,5,0) | G37: 1 | H37: =E37/F37/G37 | I37: 45 | J37: =H37*I37
B38: 金桔柠檬果蓉 | C38: =VLOOKUP(B38,原材料价格表!$B$2:$G$436,2,0) | D38: =VLOOKUP(B38,原材料价格表!$B$2:$G$436,4,0) | E38: =VLOOKUP(B38,原材料价格表!$B$2:$G$436,6,0) | F38: =VLOOKUP(B38,原材料价格表!$B$2:$G$436,5,0) | G38: 1 | H38: =E38/F38/G38 | I38: 10 | J38: =H38*I38
B39: 冰块 | C39: =VLOOKUP(B39,原材料价格表!$B$2:$G$436,2,0) | D39: =VLOOKUP(B39,原材料价格表!$B$2:$G$436,4,0) | E39: =VLOOKUP(B39,原材料价格表!$B$2:$G$436,6,0) | F39: =VLOOKUP(B39,原材料价格表!$B$2:$G$436,5,0) | G39: 1 | H39: =E39/F39/G39 | I39: 500 | J39: =H39*I39
B40: 雪域藏茶茶汤 | C40: =VLOOKUP(B40,原材料价格表!$B$2:$G$436,2,0) | D40: =VLOOKUP(B40,原材料价格表!$B$2:$G$436,4,0) | E40: =VLOOKUP(B40,原材料价格表!$B$2:$G$436,6,0) | F40: =VLOOKUP(B40,原材料价格表!$B$2:$G$436,5,0) | G40: 1 | H40: =E40/F40/G40 | I40: 200 | J40: =H40*I40
B41: 售价 | C41: 18 | D41: 售卖份量/g | E41: =SUM(I36:I40) | F41: 总成本（元） | G41: =SUM(J36:J40) | H41: 毛利/元 | I41: =C41-G41 | J41: 毛利率 | K41: =I41/C41
A44: 四果汤 | B44: 芒果 | C44: =VLOOKUP(B44,原材料价格表!$B$2:$G$436,2,0) | D44: =VLOOKUP(B44,原材料价格表!$B$2:$G$436,3,0) | E44: =VLOOKUP(B44,原材料价格表!$B$2:$G$436,6,0) | F44: =VLOOKUP(B44,原材料价格表!$B$2:$G$436,5,0) | G44: 0.55 | H44: =E44/F44/G44 | I44: 35 | J44: =H44*I44
B45: 荔枝 | C45: =VLOOKUP(B45,原材料价格表!$B$2:$G$436,2,0) | D45: =VLOOKUP(B45,原材料价格表!$B$2:$G$436,3,0) | E45: =VLOOKUP(B45,原材料价格表!$B$2:$G$436,6,0) | F45: =VLOOKUP(B45,原材料价格表!$B$2:$G$436,5,0) | G45: 1 | H45: =E45/F45/G45 | I45: 50 | J45: =H45*I45
B46: 莲子罐头 | D46: =VLOOKUP(B46,原材料价格表!$B$2:$G$436,3,0) | E46: =VLOOKUP(B46,原材料价格表!$B$2:$G$436,6,0) | F46: =VLOOKUP(B46,原材料价格表!$B$2:$G$436,5,0) | G46: 1 | H46: =E46/F46/G46 | I46: 40 | J46: =H46*I46
B47: 烧仙草罐头 | C47: =VLOOKUP(B47,原材料价格表!$B$2:$G$436,2,0) | D47: =VLOOKUP(B47,原材料价格表!$B$2:$G$436,3,0) | E47: =VLOOKUP(B47,原材料价格表!$B$2:$G$436,6,0) | F47: =VLOOKUP(B47,原材料价格表!$B$2:$G$436,5,0) | G47: 1 | H47: =E47/F47/G47 | I47: 55 | J47: =H47*I47
B48: 芋泥罐头 | C48: =VLOOKUP(B48,原材料价格表!$B$2:$G$436,2,0) | D48: =VLOOKUP(B48,原材料价格表!$B$2:$G$436,3,0) | E48: =VLOOKUP(B48,原材料价格表!$B$2:$G$436,6,0) | F48: =VLOOKUP(B48,原材料价格表!$B$2:$G$436,5,0) | G48: 1 | H48: =E48/F48/G48 | I48: 30 | J48: =H48*I48
B49: 糖桂花 | C49: =VLOOKUP(B49,原材料价格表!$B$2:$G$436,2,0) | D49: =VLOOKUP(B49,原材料价格表!$B$2:$G$436,3,0) | E49: 20 | F49: =VLOOKUP(B49,原材料价格表!$B$2:$G$436,5,0) | G49: 1 | H49: =E49/F49/G49 | I49: 20 | J49: =H49*I49
B50: 海石花 | C50: =VLOOKUP(B50,原材料价格表!$B$2:$G$436,2,0) | D50: =VLOOKUP(B50,原材料价格表!$B$2:$G$436,3,0) | E50: =VLOOKUP(B50,原材料价格表!$B$2:$G$436,6,0) | F50: =VLOOKUP(B50,原材料价格表!$B$2:$G$436,5,0) | G50: 1 | H50: =E50/F50/G50 | I50: 0.8 | J50: =H50*I50
B51: 售价 | D51: 售卖份量/g | E51: =SUM(I44:I50) | F51: 总成本（元） | G51: =SUM(J44:J50) | H51: 毛利/元 | I51: =C51-G51 | J51: 毛利率 | K51: =I51/C51
A52: 千层酥小米渣 | B52: 小米渣 | C52: =VLOOKUP(B52,原材料价格表!$B$2:$G$436,2,0) | D52: =VLOOKUP(B52,原材料价格表!$B$2:$G$436,3,0) | E52: =VLOOKUP(B52,原材料价格表!$B$2:$G$436,6,0) | F52: =VLOOKUP(B52,原材料价格表!$B$2:$G$436,5,0) | G52: 1 | H52: =E52/F52/G52 | I52: 100 | J52: =H52*I52
B53: 斑斓酱 | C53: =VLOOKUP(B53,原材料价格表!$B$2:$G$436,2,0) | D53: =VLOOKUP(B53,原材料价格表!$B$2:$G$436,3,0) | E53: =VLOOKUP(B53,原材料价格表!$B$2:$G$436,6,0) | F53: =VLOOKUP(B53,原材料价格表!$B$2:$G$436,5,0) | G53: 1 | H53: =E53/F53/G53 | I53: 10 | J53: =H53*I53
B54: 网状春卷皮 | C54: =VLOOKUP(B54,原材料价格表!$B$2:$G$436,2,0) | D54: =VLOOKUP(B54,原材料价格表!$B$2:$G$436,3,0) | E54: =VLOOKUP(B54,原材料价格表!$B$2:$G$436,6,0) | F54: =VLOOKUP(B54,原材料价格表!$B$2:$G$436,5,0) | G54: 0.9 | H54: =E54/F54/G54 | I54: 30 | J54: =H54*I54
B55: 千丝酥皮 | C55: =VLOOKUP(B55,原材料价格表!$B$2:$G$436,2,0) | D55: =VLOOKUP(B55,原材料价格表!$B$2:$G$436,3,0) | E55: =VLOOKUP(B55,原材料价格表!$B$2:$G$436,6,0) | F55: =VLOOKUP(B55,原材料价格表!$B$2:$G$436,5,0) | G55: 1 | H55: =E55/F55/G55 | I55: 30 | J55: =H55*I55
B56: 红辣椒丝 | C56: =VLOOKUP(B56,原材料价格表!$B$2:$G$436,2,0) | D56: =VLOOKUP(B56,原材料价格表!$B$2:$G$436,3,0) | E56: =VLOOKUP(B56,原材料价格表!$B$2:$G$436,6,0) | F56: =VLOOKUP(B56,原材料价格表!$B$2:$G$436,5,0) | G56: 1 | H56: =E56/F56/G56 | I56: 0.2 | J56: =H56*I56
B57: 售价 | C57: 32 | D57: 售卖份量/g | E57: =SUM(I52:I55) | F57: 总成本（元） | G57: =SUM(J52:J56) | H57: 毛利/元 | I57: =C57-G57 | J57: 毛利率 | K57: =I57/C57
A58: 桂花蜜薯 | B58: 蜜薯 | C58: =VLOOKUP(B58,原材料价格表!$B$2:$G$436,2,0) | D58: =VLOOKUP(B58,原材料价格表!$B$2:$G$436,3,0) | E58: =VLOOKUP(B58,原材料价格表!$B$2:$G$436,6,0) | F58: =VLOOKUP(B58,原材料价格表!$B$2:$G$436,5,0) | G58: 0.5 | H58: =E58/F58/G58 | I58: 100 | J58: =H58*I58
B59: 糖桂花 | C59: =VLOOKUP(B59,原材料价格表!$B$2:$G$436,2,0) | D59: =VLOOKUP(B59,原材料价格表!$B$2:$G$436,3,0) | E59: =VLOOKUP(B59,原材料价格表!$B$2:$G$436,6,0) | F59: =VLOOKUP(B59,原材料价格表!$B$2:$G$436,5,0) | G59: 1 | H59: =E59/F59/G59 | I59: 40 | J59: =H59*I59
B60: 鲜百合 | C60: =VLOOKUP(B60,原材料价格表!$B$2:$G$436,2,0) | D60: =VLOOKUP(B60,原材料价格表!$B$2:$G$436,3,0) | E60: =VLOOKUP(B60,原材料价格表!$B$2:$G$436,6,0) | F60: =VLOOKUP(B60,原材料价格表!$B$2:$G$436,5,0) | G60: 0.9 | H60: =E60/F60/G60 | I60: 5 | J60: =H60*I60
B61: 干桂花 | C61: =VLOOKUP(B61,原材料价格表!$B$2:$G$436,2,0) | D61: =VLOOKUP(B61,原材料价格表!$B$2:$G$436,3,0) | F61: =VLOOKUP(B61,原材料价格表!$B$2:$G$436,5,0) | G61: 1 | H61: =E61/F61/G61 | I61: 1 | J61: =H61*I61
B62: 售价 | C62: 38 | D62: 售卖份量/g | E62: 145 | F62: 总成本（元） | G62: =SUM(J58:J61) | H62: 毛利/元 | I62: =C62-G62 | J62: 毛利率 | K62: =I62/C62
A63: 米酿龙眼桂花冰 | B63: 冷冻龙眼肉 | C63: =VLOOKUP(B63,原材料价格表!$B$2:$G$436,2,0) | D63: =VLOOKUP(B63,原材料价格表!$B$2:$G$436,3,0) | E63: =VLOOKUP(B63,原材料价格表!$B$2:$G$436,6,0) | F63: =VLOOKUP(B63,原材料价格表!$B$2:$G$436,5,0) | G63: 1 | H63: =E63/F63/G63 | I63: 50 | J63: =H63*I63
B64: 桂花酒酿 | C64: =VLOOKUP(B64,原材料价格表!$B$2:$G$436,2,0) | D64: =VLOOKUP(B64,原材料价格表!$B$2:$G$436,3,0) | E64: =VLOOKUP(B64,原材料价格表!$B$2:$G$436,6,0) | F64: =VLOOKUP(B64,原材料价格表!$B$2:$G$436,5,0) | G64: 1 | H64: =E64/F64/G64 | I64: 30 | J64: =H64*I64
B65: 蔗糖糖浆 | C65: =VLOOKUP(B65,原材料价格表!$B$2:$G$436,2,0) | D65: =VLOOKUP(B65,原材料价格表!$B$2:$G$436,3,0) | E65: =VLOOKUP(B65,原材料价格表!$B$2:$G$436,6,0) | F65: =VLOOKUP(B65,原材料价格表!$B$2:$G$436,5,0) | G65: 1 | H65: =E65/F65/G65 | I65: 30 | J65: =H65*I65
B66: 牛乳粉 | C66: =VLOOKUP(B66,原材料价格表!$B$2:$G$436,2,0) | D66: =VLOOKUP(B66,原材料价格表!$B$2:$G$436,3,0) | E66: =VLOOKUP(B66,原材料价格表!$B$2:$G$436,6,0) | F66: =VLOOKUP(B66,原材料价格表!$B$2:$G$436,5,0) | G66: 1 | H66: =E66/F66/G66 | I66: 15 | J66: =H66*I66
B67: 冰块 | C67: =VLOOKUP(B67,原材料价格表!$B$2:$G$436,2,0) | D67: =VLOOKUP(B67,原材料价格表!$B$2:$G$436,3,0) | E67: =VLOOKUP(B67,原材料价格表!$B$2:$G$436,6,0) | F67: =VLOOKUP(B67,原材料价格表!$B$2:$G$436,5,0) | G67: 1 | H67: =E67/F67/G67 | I67: 300 | J67: =H67*I67
B68: 糯米 | C68: =VLOOKUP(B68,原材料价格表!$B$2:$G$436,2,0) | D68: =VLOOKUP(B68,原材料价格表!$B$2:$G$436,3,0) | E68: =VLOOKUP(B68,原材料价格表!$B$2:$G$436,6,0) | F68: =VLOOKUP(B68,原材料价格表!$B$2:$G$436,5,0) | G68: 2.55 | H68: =E68/F68/G68 | I68: 40 | J68: =H68*I68
B69: 干桂花 | C69: =VLOOKUP(B69,原材料价格表!$B$2:$G$436,2,0) | D69: =VLOOKUP(B69,原材料价格表!$B$2:$G$436,3,0) | E69: =VLOOKUP(B69,原材料价格表!$B$2:$G$436,6,0) | F69: =VLOOKUP(B69,原材料价格表!$B$2:$G$436,5,0) | G69: 1 | H69: =E69/F69/G69 | I69: 1 | J69: =H69*I69
B70: 鲜龙眼 | C70: =VLOOKUP(B70,原材料价格表!$B$2:$G$436,2,0) | D70: =VLOOKUP(B70,原材料价格表!$B$2:$G$436,3,0) | E70: =VLOOKUP(B70,原材料价格表!$B$2:$G$436,6,0) | F70: =VLOOKUP(B70,原材料价格表!$B$2:$G$436,5,0) | G70: 0.9 | H70: =E70/F70/G70 | I70: 10 | J70: =H70*I70
B71: 售价 | C71: 28 | D71: 售卖份量/g | E71: =SUM(I63:I70) | F71: 总成本（元） | G71: =SUM(J63:J70) | H71: 毛利/元 | I71: =C71-G71 | J71: 毛利率 | K71: =I71/C71
A72: 柿子半熟生酪 | B72: 奶油奶酪 | C72: =VLOOKUP(B72,原材料价格表!$B$2:$G$436,2,0) | D72: =VLOOKUP(B72,原材料价格表!$B$2:$G$436,3,0) | E72: =VLOOKUP(B72,原材料价格表!$B$2:$G$436,6,0) | F72: =VLOOKUP(B72,原材料价格表!$B$2:$G$436,5,0) | G72: 1 | H72: =E72/F72/G72 | I72: 80 | J72: =H72*I72
B73: 全脂牛奶 | C73: =VLOOKUP(B73,原材料价格表!$B$2:$G$436,2,0) | D73: =VLOOKUP(B73,原材料价格表!$B$2:$G$436,3,0) | E73: =VLOOKUP(B73,原材料价格表!$B$2:$G$436,6,0) | F73: =VLOOKUP(B73,原材料价格表!$B$2:$G$436,5,0) | G73: 1 | H73: =E73/F73/G73 | I73: 110 | J73: =H73*I73
B74: 百利凝胶片 | C74: =VLOOKUP(B74,原材料价格表!$B$2:$G$436,2,0) | D74: =VLOOKUP(B74,原材料价格表!$B$2:$G$436,3,0) | E74: =VLOOKUP(B74,原材料价格表!$B$2:$G$436,6,0) | F74: =VLOOKUP(B74,原材料价格表!$B$2:$G$436,5,0) | G74: 1 | H74: =E74/F74/G74 | I74: 4 | J74: =H74*I74
B75: 冷冻柿子浆 | C75: =VLOOKUP(B75,原材料价格表!$B$2:$G$436,2,0) | D75: =VLOOKUP(B75,原材料价格表!$B$2:$G$436,3,0) | E75: =VLOOKUP(B75,原材料价格表!$B$2:$G$436,6,0) | F75: =VLOOKUP(B75,原材料价格表!$B$2:$G$436,5,0) | G75: 1 | H75: =E75/F75/G75 | I75: 50 | J75: =H75*I75
B76: 白糖 | C76: =VLOOKUP(B76,原材料价格表!$B$2:$G$436,2,0) | D76: =VLOOKUP(B76,原材料价格表!$B$2:$G$436,3,0) | E76: =VLOOKUP(B76,原材料价格表!$B$2:$G$436,6,0) | F76: =VLOOKUP(B76,原材料价格表!$B$2:$G$436,5,0) | G76: 1 | H76: =E76/F76/G76 | I76: 12 | J76: =H76*I76
B77: 干桂花 | C77: =VLOOKUP(B77,原材料价格表!$B$2:$G$436,2,0) | D77: =VLOOKUP(B77,原材料价格表!$B$2:$G$436,3,0) | E77: =VLOOKUP(B77,原材料价格表!$B$2:$G$436,6,0) | F77: =VLOOKUP(B77,原材料价格表!$B$2:$G$436,5,0) | G77: 1 | H77: =E77/F77/G77 | I77: 0.5 | J77: =H77*I77
B78: 淡奶油 | C78: =VLOOKUP(B78,原材料价格表!$B$2:$G$436,2,0) | D78: =VLOOKUP(B78,原材料价格表!$B$2:$G$436,3,0) | E78: =VLOOKUP(B78,原材料价格表!$B$2:$G$436,6,0) | F78: =VLOOKUP(B78,原材料价格表!$B$2:$G$436,5,0) | G78: 1 | H78: =E78/F78/G78 | I78: 50 | J78: =H78*I78
B79: 售价 | C79: 28 | D79: 售卖份量/g | E79: =SUM(I72:I78) | F79: 总成本（元） | G79: =SUM(J72:J78) | H79: 毛利/元 | I79: =C79-G79 | J79: 毛利率 | K79: =I79/C79

Sheet 原材料价格表
A1: 分类 | B1: 原材料名称 | C1: 进货渠道 | D1: 品牌 | E1: 规格 | F1: 基础单位数量(g) | G1: 采购价格(元) | H1: 储存方式 | I1: 标准出成率 | J1: 基础单价(元/g) | K1: 备注 | L1: 分类 | M1: 是否供应链化 | N1: 付款方式
A2: 干杂 | B2: 红油 | C2: 自制 | F2: 500 | G2: 27 | H2: 常温 | I2: 0.95 | J2: 0.05 | L2: 干杂 | P2: 采购渠道：
A3: 干杂 | B3: 水 | C3: 自制 | F3: 500 | G3: 0 | I3: 1 | L3: 干杂 | P3: 1.成都牛肉供货商
B4: 冰块 | C4: 自制 | F4: 500 | G4: 0 | I4: 1 | P4: 2.绵阳蔬菜
A5: 自制酱料 | B5: 香茅酱 | C5: 自制 | F5: ='肉类、海鲜（涮菜）'!F116 | G5: ='肉类、海鲜（涮菜）'!H116 | I5: 1 | L5: 自制酱料 | P5: 3.绵阳干杂
A6: 自制酱料 | B6: 干巴菌酱 | C6: 自制 | F6: ='肉类、海鲜（涮菜）'!F140 | G6: ='肉类、海鲜（涮菜）'!H140 | I6: 1 | L6: 自制酱料 | P6: 4.绵阳海鲜
A7: 自制 | B7: 鸭屎香乌龙茶汤 | C7: 自制 | F7: =糖水铺!E26 | G7: =糖水铺!G26 | H7: 冷藏 | I7: 1 | L7: 自制 | P7: 5.酒商
A8: 自制 | B8: 山茶花茶汤 | C8: 自制 | F8: =糖水铺!E7 | G8: =糖水铺!G7 | H8: 冷藏 | I8: 1 | L8: 自制 | P8: 6.绵阳干冰
A9: 自制 | B9: 五指毛桃茶汤 | C9: 自制 | F9: =糖水铺!E17 | G9: =糖水铺!G17 | H9: 冷藏 | I9: 1 | L9: 自制 | P9: 7.虾滑群
A10: 海鲜 | B10: 虾滑 | C10: 7.虾滑群 | D10: 亚万食品 | E10: 150g*30包/件 | F10: 125 | G10: 9.17 | H10: 冷冻 | I10: 1 | J10: 0.092 | L10: 海鲜 | N10: 货到付款 | P10: 8.乌鱼片采购
A11: 海鲜 | B11: 乌鱼片 | C11: 8.乌鱼片采购 | D11: 四川双柒食品有限公司 | E11: 500g/袋 | F11: 500 | G11: 22 | H11: 冷冻 | I11: 0.95 | J11: 0.0454 | L11: 海鲜 | N11: 货到付款 | P11: 9.泓泰商贸（柠檬粉、味露、鱼露）
A12: 肉类 | B12: 雪花松板肉 | C12: 网采 | E12: 400g/袋 | F12: 400 | G12: 16 | H12: 冷冻 | I12: 1 | J12: 0.04 | L12: 肉类 | P12: 10.干茅草、五指毛桃群
A13: 肉类 | B13: 猪响皮 | C13: 网采 | D13: 土特产店铺 | E13: 称重 | F13: 500 | G13: 25 | H13: 常温 | I13: 0.95 | J13: 0.05 | L13: 肉类
A14: 肉类 | B14: 糯米午餐肉 | C14: 网采 | D14: 盛佳佳茂 | E14: 340g/罐 | F14: 340 | G14: 10.3 | H14: 常温 | I14: 1 | J14: 0.030294 | L14: 肉类
A15: 蔬菜 | B15: 干花菜 | C15: 网采 | D15: 醉川味四川花椒辣椒 | E15: 2500g/85.32元 | F15: 500 | G15: 17 | H15: 常温 | I15: 1 | J15: 0.034 | L15: 蔬菜
A16: 蔬菜 | B16: 干贡菜 | C16: 网采 | D16: 醉川味四川花椒辣椒 | E16: 称重 | F16: 500 | G16: 45.5 | H16: 常温 | I16: 1 | J16: 0.091 | L16: 蔬菜
A17: 蔬菜 | B17: 干黄花 | C17: 网采 | D17: 味江涞食品商行 | E17: 20斤/件/530元 | F17: 500 | G17: 26.5 | H17: 常温 | I17: 1 | J17: 0.053 | L17: 蔬菜
A18: 干杂 | B18: 野菜卷（成品） | C18: 网采 | D18: 惠厨食品供应商-国味缘 | E18: 170元/件 20袋/件 10根/袋 | F18: 1 | G18: =170/20/10 | H18: 冷藏 | I18: 1 | K18: 根 | L18: 干杂
A19: 干杂 | B19: 木姜子油 | C19: 网采 | E19: 780ml/瓶 | F19: 500 | G19: =41.5/780*500 | H19: 常温 | I19: 1 | L19: 干杂
A20: 干杂 | B20: 金蒜酥 | C20: 9.泓泰商贸 | E20: 500g/袋 | F20: 500 | G20: 20 | H20: 常温 | I20: 1 | J20: 0.04 | L20: 干杂
A21: 干杂 | B21: 黑松露酱 | C21: 网采 | D21: 若桑食品批发-欧萨 | E21: 500g/罐 | F21: 500 | G21: 125 | H21: 冷藏 | I21: 1 | J21: 0.25 | L21: 干杂
A22: 干杂 | B22: 墨鱼汁 | C22: 网采 | D22: 若桑食品批发-欧萨 | E22: 500g/罐 | F22: 500 | G22: 112 | H22: 冷藏 | I22: 1 | J22: 0.224 | L22: 干杂
A23: 干杂 | B23: 黄心皮蛋 | C23: 网采 | D23: 川农小温的小店 | E23: 个 | F23: 1 | G23: 1.6 | H23: 常温 | I23: 1 | J23: 1.6 | K23: 单位：个 | L23: 干杂
A24: 干杂 | B24: 春卷皮 | C24: 网采 | D24: 夜郎食味贵州特产店 | E24: 65张/斤/包 | F24: 1 | G24: 0.2 | H24: 冷藏 | I24: 1 | J24: 0.2 | K24: 单位：张 | L24: 干杂
A25: 干杂 | B25: 溏心蛋 | C25: 网采 | D25: 凡人乐旗舰店 | E25: 枚 | F25: 枚 | G25: 2 | H25: 常温 | I25: 1 | L25: 干杂
A26: 酱料 | B26: 豆腐乳 | C26: 网采 | D26: 百花串 | E26: 310g/瓶 | F26: 310 | G26: 7.17 | H26: 冷藏 | I26: 1 | J26: 0.023129 | L26: 酱料
A27: 酱料 | B27: 水豆豉 | C27: 网采 | D27: 贵山辣 | E27: 610g/瓶 | F27: 610 | G27: 7.13 | H27: 冷藏 | I27: 1 | J27: 0.011689 | L27: 酱料
A28: 干杂 | B28: 黄天鹅无菌蛋 | C28: 集采 | E28: 个 | F28: 1 | G28: 1.89 | H28: 常温15天 | I28: 1 | J28: 1.89 | K28: 单位：个 | L28: 干杂
A29: 干杂 | B29: 玫瑰乳扇 | C29: 网采 | D29: 极丝食品旗舰店 | E29: 500g/袋 | F29: 500 | G29: 34.2 | H29: 冷藏 | I29: 1 | J29: 0.0684 | L29: 干杂
A30: 酱料 | B30: 玫瑰酱 | C30: 网采 | D30: 觅滇食品专营店 | E30: 5000g/瓶 | F30: 5000 | G30: 64.5 | H30: 冷藏 | I30: 1 | J30: 0.0129 | L30: 酱料
A31: 酱料 | B31: 百香果原汁 | C31: 网采 | D31: 嘉优鲜果园 | E31: 10斤/80.8元 | F31: 500 | G31: 8.08 | H31: 冷藏 | I31: 1 | J31: 0.01616 | L31: 酱料
A32: 干杂 | B32: 干巴菌 | C32: 网采 | E32: 2斤/250元 | F32: 500 | G32: 130 | H32: 常温 | I32: 1 | J32: 0.26 | L32: 干杂
A33: 干杂 | B33: 干玫瑰花 | C33: 网采 | F33: 500 | G33: 75 | H33: 常温 | I33: 1 | J33: 0.236 | L33: 干杂
A34: 肉类 | B34: 宣威火腿 | C34: 网采 | E34: 500g/块 | F34: 500 | G34: 36.96 | H34: 冷藏 | I34: 0.9 | J34: 0.07392 | L34: 肉类
A35: 干杂 | B35: 帕玛森干酪 | C35: 网采 | E35: 200g/块 | F35: 200 | G35: 27.6 | I35: 1 | J35: 0.149 | L35: 干杂
A36: 干杂 | B36: 香草冰淇淋 | C36: 网采 | E36: 3.5kg/桶 | F36: =7*500 | G36: 120 | I36: 1 | L36: 干杂
A37: 干杂 | B37: 碧根果碎 | C37: 网采 | E37: 500g*2罐/60元 | F37: 500 | G37: 30 | I37: 1 | J37: 0.06 | L37: 干杂
A38: 干杂 | B38: 刺梨果干 | C38: 网采 | E38: 450g/罐 | F38: 450 | G38: 12.4 | H38: 常温 | I38: 1 | J38: 0.027556 | L38: 干杂
A39: 糖水铺 | B39: 刺梨原浆 | C39: 网采 | E39: 200ml/袋*10袋/件 | F39: 200 | G39: =47.41/10 | I39: 1 | L39: 糖水铺
A40: 蔬菜 | B40: 水蜜桃 | C40: 绵阳水果 | F40: 500 | G40: 25 | H40: 冷藏 | I40: 0.9 | J40: 0.05 | L40: 蔬菜 | N40: 先款后货
A41: 蔬菜 | B41: 荔枝 | C41: 绵阳水果 | E41: 颗 | F41: 1 | G41: 0.3 | H41: 冷藏 | I41: 1 | J41: 0.3 | K41: 颗 | L41: 蔬菜 | N41: 先款后货
A42: 肉类 | B42: 猪蹄 | C42: 2.绵阳蔬菜 | E42: 称重 | F42: 500 | G42: 21 | H42: 冷藏 | I42: 0.9 | J42: 0.042 | L42: 肉类 | N42: 月付
A43: 肉类 | B43: 鸡爪 | C43: 2.绵阳蔬菜 | E43: 称重 | F43: 500 | G43: 24 | H43: 冷藏 | I43: 0.75 | J43: 0.048 | L43: 肉类 | N43: 月付
A44: 蔬菜 | B44: 鲜板栗 | C44: 2.绵阳蔬菜 | E44: 称重 | F44: 500 | G44: 10 | H44: 冷藏 | I44: 1 | J44: 0.02 | L44: 蔬菜 | N44: 月付
A45: 蔬菜 | B45: 鲜百合 | C45: 2.绵阳蔬菜 | E45: 60g/袋 | F45: 60 | G45: 10 | H45: 冷藏 | I45: 0.9 | J45: 0.166667 | L45: 蔬菜 | N45: 月付
A46: 蔬菜 | B46: 血皮菜 | C46: 2.绵阳蔬菜 | E46: 称重 | F46: 500 | G46: 5 | H46: 冷藏 | I46: 0.9 | J46: 0.01 | L46: 蔬菜 | N46: 月付
A47: 蔬菜 | B47: 鲜黄花 | C47: 2.绵阳蔬菜 | E47: 称重 | F47: 500 | G47: 30 | H47: 冷藏 | I47: 0.9 | J47: 0.06 | L47: 蔬菜 | N47: 月付
A48: 蔬菜 | B48: 粗山药 | C48: 2.绵阳蔬菜 | E48: 称重 | F48: 500 | G48: 3.5 | H48: 常温 | I48: 0.9 | J48: 0.007 | L48: 蔬菜 | N48: 月付
A49: 蔬菜 | B49: 姜柄瓜 | C49: 2.绵阳蔬菜 | E49: 称重 | F49: 500 | G49: 8 | H49: 冷藏 | I49: 0.95 | J49: 0.016 | L49: 蔬菜 | N49: 月付
A50: 蔬菜 | B50: 花生芽 | C50: 2.绵阳蔬菜 | E50: 230g/袋 | F50: 230 | G50: 4.5 | H50: 冷藏 | I50: 0.95 | J50: 0.019565 | L50: 蔬菜 | N50: 月付
A51: 蔬菜 | B51: 七彩土豆 | C51: 2.绵阳蔬菜 | E51: 称重 | F51: 500 | G51: 3.5 | H51: 常温 | I51: 0.9 | J51: 0.007 | L51: 蔬菜 | N51: 月付
A52: 蔬菜 | B52: 藕 | C52: 2.绵阳蔬菜 | E52: 称重 | F52: 500 | G52: 5 | H52: 常温 | I52: 0.9 | J52: 0.01 | L52: 蔬菜 | N52: 月付
A53: 蔬菜 | B53: 黑豆腐 | C53: 2.绵阳蔬菜 | E53: 500g/盒 | F53: 500 | G53: 4.5 | H53: 冷藏 | I53: 1 | J53: 0.009 | L53: 蔬菜 | N53: 月付
... A71: 蔬菜 | B71: 香菜 | C71: 2.绵阳蔬菜 | E71: 称重 | F71: 500 | G71: 6.5 | H71: 冷藏 | I71: 0.9 | J71: 0.013 | L71: 蔬菜 | N71: 月付
A72: 蔬菜 | B72: 大香菜 | C72: 2.绵阳蔬菜 | E72: 称重 | F72: 500 | G72: 13 | H72: 冷藏 | I72: 1 | J72: 0.026 | K72: 野香菜 | L72: 蔬菜 | N72: 月付
A73: 蔬菜 | B73: 美人椒 | C73: 2.绵阳蔬菜 | E73: 称重 | F73: 500 | G73: 7 | H73: 冷藏 | I73: 1 | J73: 0.014 | L73: 蔬菜 | N73: 月付
A74: 蔬菜 | B74: 小青柠 | C74: 2.绵阳蔬菜 | E74: 称重 | F74: 500 | G74: 13 | H74: 冷藏 | I74: 1 | J74: 0.026 | L74: 蔬菜 | N74: 月付
A75: 蔬菜 | B75: 芭蕉叶 | C75: 2.绵阳蔬菜 | E75: 称重 | F75: 500 | G75: 10 | H75: 常温 | I75: 0.9 | J75: 0.02 | L75: 蔬菜 | N75: 月付
A76: 蔬菜 | B76: 绿豆芽 | C76: 2.绵阳蔬菜 | E76: 称重 | F76: 500 | G76: 1.5 | H76: 冷藏 | I76: 0.95 | J76: 0.003 | L76: 蔬菜 | N76: 月付
A77: 蔬菜 | B77: 黄瓜 | C77: 2.绵阳蔬菜 | E77: 称重 | F77: 500 | G77: 4 | H77: 冷藏 | I77: 0.9 | J77: 0.008 | L77: 蔬菜 | N77: 月付
A78: 蔬菜 | B78: 青笋 | C78: 2.绵阳蔬菜 | E78: 称重 | F78: 500 | G78: 2 | H78: 冷藏 | I78: 0.9 | J78: 0.004 | L78: 蔬菜 | N78: 月付
A79: 蔬菜 | B79: 豆皮 | C79: 2.绵阳蔬菜 | E79: 称重 | F79: 500 | G79: 5 | H79: 冷藏 | I79: 1 | J79: 0.01 | L79: 蔬菜 | N79: 月付
A80: 蔬菜 | B80: 凉面 | C80: 2.绵阳蔬菜 | E80: 称重 | F80: 500 | G80: 3 | H80: 冷藏 | I80: 1 | J80: 0.006 | L80: 蔬菜 | N80: 月付
A81: 蔬菜 | B81: 二荆条 | C81: 2.绵阳蔬菜 | E81: 称重 | F81: 500 | G81: 5 | H81: 冷藏 | I81: 1 | J81: 0.01 | L81: 蔬菜 | N81: 月付
A82: 蔬菜 | B82: 黄豆芽 | C82: 2.绵阳蔬菜 | E82: 称重 | F82: 500 | G82: 1.5 | H82: 冷藏 | I82: 0.95 | J82: 0.003 | L82: 蔬菜 | N82: 月付
A83: 蔬菜 | B83: 小葱 | C83: 2.绵阳蔬菜 | E83: 称重 | F83: 500 | G83: 3.8 | H83: 冷藏 | I83: 1 | J83: 0.0076 | L83: 蔬菜 | N83: 月付
A84: 蔬菜 | B84: 大葱 | C84: 2.绵阳蔬菜 | E84: 称重 | F84: 500 | G84: 2 | H84: 冷藏 | I84: 1 | J84: 0.004 | L84: 蔬菜 | N84: 月付
A85: 蔬菜 | B85: 法香 | C85: 2.绵阳蔬菜 | E85: 称重 | F85: 500 | G85: 7 | H85: 冷藏 | I85: 1 | J85: 0.014 | L85: 蔬菜 | N85: 月付
A86: 蔬菜 | B86: 千叶吊兰 | C86: 2.绵阳蔬菜 | E86: 盆 | F86: 1盆 | G86: 18 | H86: 常温 | I86: 1 | L86: 蔬菜 | N86: 月付
A87: 蔬菜 | B87: 羊齿叶 | C87: 2.绵阳蔬菜 | E87: 称重 | H87: 常温 | I87: 1 | L87: 蔬菜 | N87: 月付
A88: 蔬菜 | B88: 薄荷 | C88: 2.绵阳蔬菜 | E88: 称重 | F88: 500 | G88: 9 | H88: 冷藏 | I88: 0.85 | J88: 0.018 | L88: 蔬菜 | N88: 月付
A89: 蔬菜 | B89: 紫苏叶 | C89: 2.绵阳蔬菜 | E89: 称重 | F89: 500 | G89: 8 | H89: 冷藏 | I89: 1 | J89: 0.016 | L89: 蔬菜 | N89: 月付
A90: 蔬菜 | B90: 紫苏碎 | C90: 2.绵阳蔬菜 | E90: 称重 | F90: 500 | G90: 15 | H90: 冷藏 | I90: 1 | J90: 0.03 | L90: 蔬菜 | N90: 月付
A91: 蔬菜 | B91: 斑斓叶 | C91: 2.绵阳蔬菜 | E91: 称重 | F91: 500 | G91: 10 | H91: 冷藏 | I91: 1 | J91: 0.02 | L91: 蔬菜 | N91: 月付
A92: 蔬菜 | B92: 莲白 | C92: 2.绵阳蔬菜 | E92: 称重 | F92: 500 | G92: 1 | H92: 冷藏 | I92: 1 | J92: 0.002 | L92: 蔬菜 | N92: 月付
A93: 蔬菜 | B93: 羽衣甘蓝 | C93: 2.绵阳蔬菜 | E93: 称重 | F93: 500 | G93: 8 | H93: 常温 | I93: 1 | J93: 0.016 | L93: 蔬菜 | N93: 月付
A94: 蔬菜 | B94: 红叶生菜 | C94: 2.绵阳蔬菜 | E94: 称重 | F94: 500 | G94: 7 | H94: 常温 | I94: 1 | J94: 0.014 | L94: 蔬菜 | N94: 月付
A95: 蔬菜 | B95: 甜玉米 | C95: 2.绵阳蔬菜 | E95: 称重 | F95: 500 | G95: 2.3 | H95: 冷藏 | I95: 0.7 | J95: 0.0046 | L95: 蔬菜 | N95: 月付
A96: 蔬菜 | B96: 口蘑 | C96: 2.绵阳蔬菜 | E96: 称重 | F96: 500 | G96: 11 | H96: 冷藏 | I96: 1 | J96: 0.022 | L96: 蔬菜 | N96: 月付
A97: 蔬菜 | B97: 仔姜 | C97: 2.绵阳蔬菜 | E97: 称重 | F97: 500 | G97: 7 | H97: 冷藏 | I97: 1 | J97: 0.014 | L97: 蔬菜 | N97: 月付
A98: 蔬菜 | B98: 洋葱 | C98: 2.绵阳蔬菜 | E98: 称重 | F98: 500 | G98: 6.4 | H98: 冷藏 | I98: 0.95 | J98: 0.0128 | L98: 蔬菜 | N98: 月付
A99: 蔬菜 | B99: 粽叶 | C99: 2.绵阳蔬菜 | E99: 称重 | F99: 1 | G99: =8/80 | H99: 冷藏 | I99: 1 | K99: 单位：张 | L99: 蔬菜 | N99: 月付
A100: 蔬菜 | B100: 茴香苗 | C100: 2.绵阳蔬菜 | E100: 称重 | F100: 500 | G100: 9 | H100: 冷藏 | I100: 0.9 | J100: 0.018 | L100: 蔬菜 | N100: 月付
A101: 蔬菜 | B101: 白芹菜 | C101: 2.绵阳蔬菜 | E101: 称重 | F101: 500 | G101: 3.5 | H101: 冷藏 | I101: 1 | J101: 0.007 | L101: 蔬菜 | N101: 月付
A102: 肉类 | B102: 猪肉沫 | C102: 2.绵阳蔬菜 | E102: 称重 | F102: 500 | G102: 10.5 | H102: 冷藏 | I102: 1 | J102: 0.021 | L102: 肉类 | N102: 月付
A103: 蔬菜 | B103: 饺子皮 | C103: 2.绵阳蔬菜 | E103: 称重 | F103: 500 | G103: 3 | H103: 冷藏 | I103: 1 | J103: 0.006 | L103: 蔬菜 | N103: 月付
A104: 肉类 | B104: 猪肉 | C104: 2.绵阳蔬菜 | E104: 称重 | F104: 500 | G104: 10 | I104: 1 | J104: 0.02 | L104: 肉类 | N104: 月付
A105: 蔬菜 | B105: 仔姜 | C105: 2.绵阳蔬菜 | E105: 称重 | F105: 500 | G105: 7 | I105: 1 | J105: 0.014 | L105: 蔬菜 | N105: 月付
A106: 海鲜 | B106: 罗非鱼 | C106: 4.绵阳海鲜 | E106: 条 | F106: 1 | G106: 17 | H106: 水养 | I106: 1 | J106: 17 | K106: 单位：条 | L106: 海鲜 | N106: 月付
A107: 海鲜 | B107: 基围虾 | C107: 4.绵阳海鲜 | E107: 20g/只 | F107: 1 | G107: 2 | H107: 水养 | I107: 1 | J107: 2 | K107: 单位：只 | L107: 海鲜 | N107: 月付
A108: 海鲜 | B108: 10头鲍 | C108: 4.绵阳海鲜 | E108: 50g/个 | F108: 1 | G108: 6.5 | H108: 水养 | I108: 1 | J108: 6.5 | K108: 单位：只 | L108: 海鲜 | N108: 月付
A109: 海鲜 | B109: 小管 | C109: 4.绵阳海鲜 | E109: 个 | F109: 1 | G109: 8 | H109: 冷冻 | I109: 1 | J109: 8 | K109: 单位：只 | L109: 海鲜 | N109: 月付
A110: 海鲜 | B110: 生蚝 | C110: 4.绵阳海鲜 | E110: 个 | F110: 1 | G110: 3.5 | H110: 水养 | I110: 1 | J110: 3.5 | K110: 单位：只 | L110: 海鲜 | N110: 月付
A111: 蔬菜 | B111: 海带丝 | C111: 3.绵阳干杂 | E111: 称重 | F111: 500 | G111: 8 | H111: 冷藏 | I111: 1 | J111: 0.016 | L111: 蔬菜 | N111: 月付
A112: 蔬菜 | B112: 泡萝卜 | C112: 3.绵阳干杂 | E112: 称重 | F112: 500 | G112: 4 | H112: 冷藏 | I112: 0.95 | J112: 0.008 | L112: 蔬菜 | N112: 月付
A113: 干杂 | B113: 色拉油 | C113: 3.绵阳干杂 | F113: 500 | G113: 5.1 | H113: 常温 | I113: 1 | J113: 0.0102 | L113: 干杂 | N113: 月付
A114: 干杂 | B114: 菜籽油 | C114: 3.绵阳干杂 | E114: 5000g/桶 | F114: 500 | G114: 7.2 | H114: 常温 | I114: 1 | J114: 0.013 | L114: 干杂 | N114: 月付
A115: 干杂 | B115: 鸡精 | C115: 3.绵阳干杂 | D115: 豪吉 | E115: 2500g/袋 | F115: 500 | G115: =67.5/5 | H115: 常温 | I115: 1 | L115: 干杂 | N115: 月付
A116: 干杂 | B116: 味精 | C116: 3.绵阳干杂 | D116: 国泰 | E116: 454g/袋 | F116: 454 | G116: 7.95 | H116: 常温 | I116: 1 | J116: 0.017511 | L116: 干杂 | N116: 月付
A117: 干杂 | B117: 盐 | C117: 3.绵阳干杂 | D117: 久大 | E117: 350g/袋 | F117: 350 | G117: 1.07 | H117: 常温 | I117: 1 | J117: 0.003057 | L117: 干杂 | N117: 月付
...
